Workbook

Sheet Painel
G32: Outputs:
G33: a) Perfil Setorial: predomínio do Terceiro Setor (65%), seguido pelo Privado (20%) e Público (11%), indicando um ecossistema movido por filantropia e cooperação técnica. b) Natureza das Organizações: presença de Grantmakers e Think Tanks, sinalizando alta capacidade de financiamento e formulação de estratégias. c) Eixo Temático Central: O nexo "Land, Food and Forest" é a prioridade em +60% do mapa. d) Influência Secundária: Building & Transport emergem como áreas de suporte para a descarbonização das cadeias produtivas. e) Alcance Geográfico: 74% possuem atuação Nacional, com 18% de conexões Internacionais. f) Lente Territorial: a Amazônia é o bioma prioritário absoluto, seguido pelo Cerrado e Mata Atlântica; biomas como Pampa e Caatinga aparecem de forma periférica.

Sheet Stakeholder list
B2: Stakeholder Ecosystem Mapping
B4: Project: Strategic ecosystem pre-assessment and stakeholders`mapping in Brazil
B5: Last update: 11/02/2026
B6: ID | C6: Stakeholder | D6: Organization's sector | E6: Type of organization | F6: Description of organization & contribution to systemic transition (strategic focus) | G6: Territorial focus (national, region, city) | H6: Primary impact area (sector of interest / Nexuses) | I6: Primary Territory lens (Biome) | J6: Secondary Territory lens (Biome) | K6: Biome focus rationale (only when the organization has explicit project/action targeting by biome) | L6: Role within the ecosystem | M6: Position in the value chain | N6: Potential partnership with IKF | O6: Headquarters location | P6: Funding Role | Q6: Contact (name, role and e-mail) | R6: Site / related links | S6: General notes / Refs | T6: MEL type / approach
B7: 1 | C7: Instituto Ibirapitanga | D7: Civil Society Organization (CSO) | E7: Philanthropy foundations | F7: A grantmaking organization that supports organizations, movements, and collectives to drive structural transformations, with a focus on democracy/civic freedoms, racial equity, and agendas such as fair and sustainable food systems. | G7: National | H7: "Land, Food and Forest" | I7: Amazonia | K7: Grantmaking is organized by themes such as democracy, racial equity and fair food systems, not by ecological territories. Funding can reach many regions, but biome targeting is not used as an allocation rule. | L7: Funder, Strategic partner | M7: Midstream | N7: Co-funding partner | O7: Rio de Janeiro, RJ, Brazil | P7: Donor | Q7: André Degenszajn (Executive Director) | R7: https://ibirapitanga.org.br/ | S7: Could be a relevant partner for co-funding efforts on food systems in the Amazon. | T7: —
B8: 2 | C8: Instituto Serrapilheira | D8: Civil Society Organization (CSO) | E8: Philanthropy foundations | F8: A private, non-profit philanthropic institute that promotes science in Brazil; it funds research, training, and journalism/media initiatives to strengthen evidence-based public and private decision-making. | G8: National | H8: "Land, Food and Forest" | K8: Portfolio follows scientific fields, fellowships and science communication priorities. Projects may occur in different places, yet the institute does not manage programs using biomes as the operating unit. | L8: Funder, Technical assistance / research, Strategic partner | M8: Midstream | N8: Co-funding partner | O8: Rio de Janeiro, RJ, Brazil | P8: Donor | Q8: Hugo Aguilaniu (President) | R8: https://serrapilheira.org/ | S8: Could be a relevant partner for co-funding efforts on science-based approaches, advocacy and communications | T8: —
B9: 3 | C9: Fundo Brasileiro para a Biodiversidade (FUNBIO) | D9: Civil Society Organization (CSO) | E9: Philanthropy foundations | F9: A national, private, non-profit financial mechanism that mobilizes and manages resources for biodiversity conservation, supporting initiatives, projects, and financing arrangements in partnership with government, the private sector, and civil society. | G9: National | H9: "Land, Food and Forest" | I9: Amazonia, Caatinga, Cerrado | J9: Mata&Atlântica, Pantanal, Pampa, Coastal&maritime | K9: Multi biome financial mechanism with recurring biodiversity pipelines in Amazonia and Cerrado. Other biomes appear through specific funds and projects, but with lower frequency in the core flow of managed initiatives. | L9: Funder, Capital provider / Financial intermediary | M9: Midstream | N9: Co-funding partner | O9: Rio de Janeiro, RJ, Brazil | P9: Re-granter | Q9: Rosa Lemos de Sá (Executive Director) | R9: https://www.funbio.org.br/ | S9: Potential co-funding, strategic partner & regranter to work in all Brazilan Biomes, with trackrecord as a financial mechanism to work on bioodiversituy, climate change and civil society stregnthening in all regions with a diverisity of national and international partenrs | T9: —
B10: 4 | C10: Instituto Clima e Sociedade (iCS) | D10: Civil Society Organization (CSO) | E10: Monitoring, Evaluation, and Learning | F10: A regranter organization that supports tackling climate change by funding agendas and actors capable of accelerating a just and effective transition to a low-carbon economy. | G10: National | H10: Buildings & Transport, Energy, "Land, Food and Forest" | I10: Amazonia, Caatinga, Cerrado | J10: Mata&Atlântica, Pantanal, Pampa, Coastal&maritime | K10: Grantmaking frequently connects climate and land use priorities in Amazonia, Cerrado and Caatinga. Additional biomes are supported through partners and calls, but are not the main recurring anchors of the portfolio. | L10: Funder, Strategic partner, Convenor/enablers, Capital provider / Financial intermediary | M10: Upstream | N10: Strategic partner | O10: Rio de Janeiro, RJ, Brazil | P10: Re-granter | Q10: Maria Netto Schnider | R10: https://climaesociedade.org/ | S10: Regrenter organization well posionetd in Brazil in different arenas to address climate change issues | T10: Portfolio impact monitoring & strategic evaluation of climate programs and climate finance
B11: 5 | C11: Instituto Cultura, Comunicação e Incidência (ICCI) | D11: Civil Society Organization (CSO) | E11: Philanthropy foundations | F11: A non-profit regranting organization focused on strengthening strategic communication to advance climate, democracy, and justice agendas, creating social demand for public policy and impactful private action. | G11: National | H11: Buildings & Transport, Energy, "Land, Food and Forest" | K11: Work is centered on strategic communication and policy influence rather than place based delivery. Campaign geography varies by agenda, so no stable biome delimitation is consistently observable. | L11: Project developer / Implementer, Policy influence / regulation | M11: Midstream | N11: Grant recipient | O11: Rio de Janeiro, RJ, Brazil | P11: Re-granter | Q11: Marco Kelson Kertzman | R11: https://www.iccibr.org/en/home | S11: A new player with great potential to advance climate change communication strategies in Brazil. | T11: —
B12: 6 | C12: Grupo de Institutos, Fundações e Empresas (GIFE) | D12: Civil Society Organization (CSO) | E12: Multi-stakeholder initiatives | F12: An association/platform within Brazil’s philanthropy and private social investment ecosystem; it convenes a network, produces knowledge, and strengthens institutional capacities for strategic and coordinated action. | G12: National | H12: Buildings & Transport, Energy, "Land, Food and Forest" | K12: Acts as a philanthropy platform focused on standards, learning and capacity building. Its territorial reach depends on members and partners, making biome classification non essential for its operating model. | L12: Convenor/enablers | M12: Upstream | N12: Strategic partner | O12: São Paulo, SP, Brazil | P12: Grantee | Q12: Carolla Matarazzo (Chairman) | R12: https://gife.org.br/ | S12: The most relevant network of Philanthropies in Brazil. Could be a strategic partner to address IKF workin Brazil. | T12: —
B13: 7 | C13: Movimento Bem Maior (MBM) | D13: Civil Society Organization (CSO) | E13: Alliances | F13: A philanthropic movement/network that connects donors, organizations, and partners for systemic transformation, promoting a culture of giving, active citizenship, and the strengthening of the third sector, specially philanthropies in Brazil. | G13: National | H13: Buildings & Transport, "Land, Food and Forest" | I13: Amazonia | K13: Network to mobilize giving and strengthen civil society across Brazil. Territorial footprint is partner driven and campaign driven, without a consistent program design structured by biome boundaries. | L13: Funder, Convenor/enablers | M13: Upstream | N13: Co-funding partner | O13: São Paulo, SP, Brazil | P13: Donor | Q13: Carolla Matarazzo (Executive Director) | R13: https://movimentobemmaior.org.br/ | S13: A Philanthropy established 5 years ago by 9 business leaders to enhance the grant making space in Brazil. Looking foward to co-finance strategies with other philanthropies (national and international). Could be a strategic partner for IKF in Brazil. | T13: —
B14: 8 | C14: Instituto Beija | D14: Civil Society Organization (CSO) | E14: Alliances | F14: a social impact organization that promotes a positive impact in the philanthropic ecosystem by fostering creativity, innovation, and collaboration, together with the engagement of civil society, the private sector and the government to solve systemic problems | G14: National | H14: Buildings & Transport, Energy, "Land, Food and Forest", Emergency response | K14: NA | L14: Funder, Convenor/enablers | M14: Upstream | N14: Co-funding partner | O14: Rio de Janeiro, RJ, Brazil | P14: Donor | Q14: Cristiane Sultani (Funder and Chairman) | R14: https://institutobeja.org/homepage/ | S14: A recently established Philantropy, with a similar role of Movoimento Bem Maior, to advance the givin culture in Brazil. Could be a relevant co-funder and strategic partner for IKF in Brazil. | T14: —
B15: 9 | C15: Open Society Foundations | D15: Funders | E15: Philanthropy foundations | F15: A global grantmaking philanthropic foundation focused on rights, equity, justice, democracy, and human rights; it supports organizations and initiatives in multiple countries with a focus on structural change. | G15: Cross-border / international | H15: Buildings & Transport, Emergency response, Energy, "Land, Food and Forest" | I15: Amazonia | K15: Global rights and democracy funder with broad country portfolios. In this mapping, Brazil support is not publicly organized in a way that allows a consistent biome based segmentation, but has a mention about impact in Amazon region. | L15: Funder, Strategic partner | M15: Upstream | N15: Co-funding partner | O15: New York, NY, USA | P15: Donor | Q15: Pedro Abramovay (Vice-President) | R15: https://www.opensocietyfoundations.org/newsroom/a-open-society-na-america-latina-e-no-caribe/pt | S15: They have a strong presence in Brazil. Could be a strategic partner, specially to give inputs on strategy development, approaches and lessosn learned. | T15: —
B16: 10 | C16: Instituto Ethos | D16: Civil Society Organization (CSO) | E16: Industry platforms and sectoral initiatives | F16: A civil society organization network that mobilizes and supports companies toward socially responsible and sustainable management; it develops tools, indicators, and convening efforts to strengthen socio-environmental integrity and influence policy. | G16: National | H16: Buildings & Transport, Energy, "Land, Food and Forest" | I16: Amazonia | J16: Mata&Atlântica, Pantanal, Pampa, Coastal&maritime | K16: Corporate integrity and sustainability work often engages high deforestation risk supply chains, making Amazonia the most recurrent reference. National advocacy and tools also apply beyond Amazonia, but not as a biome specific portfolio. | L16: Convenor/enablers, Policy influence / regulation | M16: Upstream | N16: Strategic partner | O16: São Paulo, SP, Brazil | P16: Grantee | Q16: Caio Magri (President) | R16: https://www.ethos.org.br/ | S16: Together with GIFE (Philantropy network), Ethos was stablished in Brazil as strong network to address social corporate responsability in the 90's. Would be interesting to talk to them to test their apetite to collaborate with IKF Impact Areas strategies. | T16: —
B17: 11 | C17: Instituto para o Desenvolvimento do Investimento Social (IDIS) | D17: Civil Society Organization (CSO) | E17: Think tanks | F17: A civil society organization that inspires, supports, and expands private social investment and its impact; it works through consulting/strategy, knowledge production, and strengthening the philanthropic ecosystem. | G17: National | H17: Buildings & Transport, Energy, "Land, Food and Forest" | K17: Operates as a philanthropy and social investment advisor and ecosystem builder. Workstreams are instrument and strategy based, so biome delimitation is not a meaningful organizing lens. | L17: Technical assistance / research, Convenor/enablers | M17: Upstream | N17: Grant recipient | O17: São Paulo, SP, Brazil | P17: Grantee | Q17: Paula Jancso Fabiani | R17: https://www.idis.org.br/ | S17: Provide services to develop civil society organizations in Brazil. Hosts and endowment fund to develop Philantropies in Brazil. | T17: —
B18: 12 | C18: Instituto Climate Ventures Brasil (Climate Ventures) | D18: Civil Society Organization (CSO) | E18: Think tanks | F18: A think-and-do tank that coordinates multi-stakeholder action and produces knowledge for systemic climate solutions; it connects actors (business, government, finance, and civil society) to accelerate a just transition and climate innovation. | G18: National | H18: Buildings & Transport, Energy, "Land, Food and Forest" | I18: Amazonia, Caatinga, Cerrado | J18: Mata&Atlântica, Pantanal, Pampa, Coastal&maritime | K18: Coordinates climate solutions with strong land use and regional transition interfaces, often most salient in Amazonia, Cerrado and Caatinga. Other biomes enter through specific coalitions, not as the primary recurring focus. | L18: Convenor/enablers, Project developer / Implementer | M18: Midstream | N18: Grant recipient | O18: São Paulo, SP, Brazil | P18: Grantee | Q18: Daniel Contrucci & Ricardo Gravnina (Co-Directors) | R18: https://www.climateventures.co/ | S18: Could be an important grantee in the cosytem to address climate solutions in Brazil. | T18: —
B19: 13 | C19: The Climate Group | D19: Civil Society Organization (CSO) | E19: Multi-stakeholder initiatives | F19: An international non-profit organization that runs corporate initiatives and coalitions (e.g., in energy/transport/industry) to accelerate net-zero targets, acting as a secretariat for alliances and mobilizing sectoral commitments. | G19: Cross-border / international | H19: Buildings & Transport, Energy | K19: Runs global corporate coalitions and sector commitments. Brazil engagement is typically framed by companies and policies, not by territorially delimited biome programs. | L19: Convenor/enablers, Strategic partner | M19: Upstream | N19: Grant recipient | O19: London, United Kingdom | P19: Grantee | Q19: Champa Patel (Global Governance Director) | R19: https://www.theclimategroup.org/ | S19: Potential partner. Intrested in working more in Brazil. | T19: —
B20: 14 | C20: Fundação Maria Cecilia Souto Vidigal | D20: Funders | E20: Philanthropy foundations | F20: A civil society organization focused on early childhood; it mobilizes leaders, supports governments and public policy, and produces evidence to reduce inequalities from the very beginning of life. | G20: National | K20: Focuses on early childhood evidence and public policy adoption by states and municipalities. Implementation geography is administrative and service based, not ecosystem based. | L20: Funder, Strategic partner | M20: Upstream | N20: Co-funding partner | O20: São Paulo, SP, Brazil | P20: Donor | Q20: Mariana Luz (Executive Director) | R20: https://fundacaomariacecilia.org.br/ | S20: Explore possibilities to be a partner. The largest endowment fund in Brazil. | T20: —
B21: 15 | C21: Fundação Tide Setúbal | D21: Funders | E21: Philanthropy foundations | F21: A foundation focused on social justice and the sustainable development of urban peripheries; it fosters initiatives and connects the state, research, and civil society to tackle socio-spatial inequalities and influence policy. | G21: National | J21: Mata&Atlântica | K21: Prioritizes urban peripheries and socio spatial inequality agendas. The operating territory is metropolitan and social, so biomes are not used to define programs. | L21: Funder, Territorial anchor | M21: Upstream | N21: Co-funding partner | O21: São Paulo, SP, Brazil | P21: Donor | Q21: Mariana Almeida (Executive Director) | R21: https://fundacaotidesetubal.org.br/ | S21: Could be a co-funding partener in urban startegies in targeted cities (as SP), supporting vulnerable comunities. | T21: —
B22: 16 | C22: Fundação Arymax | D22: Funders | E22: Philanthropy foundations | F22: A philanthropic foundation (venture philanthropy) focused on productive inclusion, employability, and organizational strengthening; it supports scalable solutions and a culture of evaluation/effectiveness to expand social impact. | G22: National | H22: Emergency response, "Land, Food and Forest" | K22: Venture philanthropy for employability and productive inclusion, oriented to scalable solutions and organizational strengthening. No consistent biome targeting appears in how programs are selected or reported. | L22: Funder, Strategic partner | M22: Upstream | N22: Co-funding partner | O22: São Paulo, SP, Brazil | P22: Donor | Q22: Viviane Naigeborin (Executive Director) | R22: https://arymax.org.br/ | S22: Potential co-funding partner in Social Impact Business (SIB) in Brazil. The org. Lead helped establishing policies and frameworks and is a reference on SIB in Brazil. | T22: —
B23: 17 | C23: Instituto Talanoa | D23: Civil Society Organization (CSO) | E23: Monitoring, Evaluation, and Learning | F23: An independent think tank dedicated to climate policy in Brazil; it combines data, science, and dialogue to monitor, analyze, and influence public policy and climate governance, increasing transparency and decision quality. | G23: National | H23: Buildings & Transport, Energy, "Land, Food and Forest" | I23: Amazonia, Caatinga, Cerrado | J23: Mata&Atlântica, Pantanal, Pampa, Coastal&maritime | K23: Produces climate governance analysis where Amazonia and Cerrado repeatedly dominate national debates on land use and NDC ambition. Other biomes are covered in broader policy discussion rather than dedicated biome programs. | L23: Technical assistance / research, Policy influence / regulation | M23: Midstream | N23: Strategic partner | O23: Brasília, DF, Brazil | P23: Grantee | Q23: Natalie Unterstell | R23: https://institutotalanoa.org/ | S23: A relevant thecnical partner in Brazil (policy, adaptation and mitigation) | T23: Climate policy monitoring, data-driven analysis and transparency of climate governance
B24: 18 | C24: Instituto Alana | D24: Civil Society Organization (CSO) | E24: Philanthropy foundations | F24: A civil society organization focused on the rights of children and adolescents; it works through advocacy, communication, and partnerships to ensure priority for childhood and promote integral development with socio-environmental justice. | G24: National | H24: "Land, Food and Forest" | I24: Amazonia, Caatinga, Cerrado | J24: Mata&Atlântica | K24: Works on children and adolescent rights with advocacy and communication strategies. Actions are not designed around biome defined geographies. | L24: Funder, Policy influence / regulation, Strategic partner , Community legitimacy / proximate leadership | M24: Midstream | N24: Co-funding partner | O24: São Paulo, SP, Brazil | P24: Donor | Q24: Ana Lúcia Villela (President) & Marcos Nisti (Vice-President) | R24: https://alana.org.br/ | S24: Could be a co-finding partner on targeted audience. Works a lot in advocacy, campaigns and information foucesed on young generation) | T24: —
B25: 19 | C25: Itaúsa (Itaúsa S.A.) | D25: Private sector | E25: Institutional Investors | F25: A publicly listed holding company; it invests in a portfolio of companies and can influence the transition through governance, ESG strategy, capital allocation, and engagement for sustainable development and positive impact. | G25: National | H25: Buildings & Transport, Energy, "Land, Food and Forest" | K25: Influence is exercised through portfolio governance, ESG and capital allocation. No public strategy indicates biome specific territorial programming. | L25: Strategic partner, Capital provider / Financial intermediary | M25: Upstream | N25: Co-funding partner | O25: São Paulo, SP, Brazil | P25: Re-granter | Q25: Marcelo Furtado (Sustainable Head) | R25: https://www.itausa.com.br/ | S25: Interested in the climate change. Alredy finance a lot of different effort, hubs and networks. Could be a co-funding partner for IKF in Brazil. | T25: —
B26: 20 | C26: Instituto Arapyaú | D26: Civil Society Organization (CSO) | E26: Philanthropy foundations | F26: A Brazilian philanthropic organization that fosters and incubates networks and structuring initiatives to promote fair, inclusive, and low-carbon development; it convenes public/private actors and civil society to advance systemic solutions in climate, nature, and the economy. | G26: National | H26: Buildings & Transport, Energy, "Land, Food and Forest" | I26: Amazonia | J26: Mata&Atlântica | K26: Sustained territorial convening and networks are most visibly linked to Amazonia, with additional recurring work connected to Mata Atlântica agendas. The biome tagging reflects where long term coalitions and place based initiatives concentrate. | L26: Funder, Strategic partner, Territorial anchor | M26: Midstream | N26: Co-funding partner | O26: São Paulo, SP, Brazil | P26: Donor | Q26: Renata Piazzon (CEO) | R26: https://arapyau.org.br/ | S26: Relevant partner to co-fund initiatives in teh Amazon. Also works a lot in terrritorial development in Bahia. Guilherme Leal's philanthropy (one of Natura's owner) | T26: —
B27: 21 | C27: Instituto Semeia | D27: Civil Society Organization (CSO) | E27: Philanthropy foundations | F27: A non-profit philanthropic organization focused on enhancing the sustainable socioeconomic development of parks and protected areas, supporting management models, partnerships, and knowledge for conservation and visitation. | G27: National | H27: "Land, Food and Forest" | I27: Amazonia, Cerrado | J27: Mata&Atlântica, Pantanal, Pampa, Coastal&maritime | K27: Parks and protected areas agenda spans multiple regions, with recurring relevance in Amazonia and Cerrado due to scale and pressure dynamics. Other biomes appear through specific protected area partnerships and knowledge products. | L27: Technical assistance / research, Project developer / Implementer, Funder | M27: Midstream | N27: Co-funding partner | O27: São Paulo, SP, Brazil | P27: Donor | Q27: Fernando Pieroni (Executive Director) | R27: https://semeia.org.br/ | S27: Interesting partner to understand and potentially co-fund strategies to address Public and Private Prtnerships (PPPs) in IKF impact areas. Perdo Passos' philanthropy (one of Natura's owner). | T27: —
B28: 22 | C28: The David and Lucile Packard Foundation | D28: Funders | E28: Philanthropy foundations | F28: An international grantmaking philanthropic foundation that funds agendas such as conservation/restoration of natural systems, climate, and community strengthening; it supports organizations and coalitions for structural, evidence-based change. | G28: Cross-border / international | H28: Energy, "Land, Food and Forest" | K28: International grantmaker with broad environment and community portfolios. This list does not provide a stable Brazil facing biome structured program line to classify. | L28: Funder, Strategic partner | M28: Upstream | N28: Co-funding partner | O28: Los Altos, CA, USA | P28: Donor | R28: https://www.packard.org/ | S28: Potential partner in Brazil. Explore a range of sustainable territorial development approaches and lessons lerned funding initiatives in Brazil. | T28: —
B29: 23 | C29: Alcoa | D29: Private sector | E29: Private companies (large / leading) | F29: A global company in the aluminum sector (bauxite, alumina, and aluminum); it contributes to the transition through industrial decarbonization, ESG standards, traceability, and engagement with supply chains and the territories where it operates. | G29: Cross-border / international | H29: Buildings & Transport, Energy | I29: Amazonia | J29: Coastal&maritime | K29: Operational footprint and risk management are most consistently associated with Amazonia. Coastal maritime appears as a secondary interface through logistics and export corridors rather than a dedicated conservation program. | L29: Strategic partner, Implementation capacity (delivery) | M29: Downstream | N29: Co-funding partner | O29: Pittsburgh, PA, USA | P29: Donor | R29: https://www.alcoa.com/brasil/pt | S29: Could be a potential co-funding partner in targeted geographies, linkes to IKF impact areas. | T29: —
B30: 24 | C30: Norsk Hydro ASA (Hydro) | D30: Private sector | E30: Private companies (large / leading) | F30: A global leader in aluminum and renewable energy; it can drive the transition through circular economy practices, emissions reductions, materials innovation, socio-environmental governance, and investment in low-carbon value chains. | G30: Cross-border / international | H30: Buildings & Transport, Energy | I30: Amazonia | J30: Coastal&maritime | K30: Industrial and mining assets create a strong linkage to Amazonia. Coastal maritime is included as a secondary lens due to transport and port logistics interfaces that shape impacts and mitigation needs. | L30: Strategic partner, Implementation capacity (delivery) | M30: Midstream | N30: Co-funding partner | O30: Oslo, Norway | P30: Donor | R30: https://www.hydro.com/br | S30: Could be a potential co-funding partner in targeted geographies, linkes to IKF impact areas. | T30: —
B31: 25 | C31: Instituto Socioambiental (ISA) | D31: Civil Society Organization (CSO) | E31: Local implementers | F31: A Brazilian NGO (OSCIP) that defends the rights and territories of Indigenous Peoples and traditional communities and protects socio-environmental heritage; it contributes through advocacy, monitoring, and integrated solutions for conservation and socio-environmental justice. | G31: National | H31: "Land, Food and Forest" | I31: Amazonia | J31: Mata&Atlântica | K31: Long running rights and territorial governance work is strongly anchored in Amazonia. A secondary linkage to Mata Atlântica reflects additional initiatives and advocacy connected to that biome domain. | L31: Project developer / Implementer, Community legitimacy / proximate leadership | M31: Midstream | N31: Implementing partner | O31: São Paulo, SP, Brazil | P31: Grantee | Q31: Adriana Ramos (Policy Director) | T31: —
B32: 26 | C32: The Nature Conservancy Brasil (TNC Brasil) | D32: Civil Society Organization (CSO) | E32: Local implementers | F32: A science-based international conservation NGO; it develops local solutions to protect land and water, restore ecosystems, and design financing/arrangements for conservation, connecting the public and private sectors and communities. | G32: Cross-border / international | H32: "Land, Food and Forest" | I32: Amazonia, Cerrado | J32: Mata&Atlântica, Coastal&maritime | K32: Territorial programs and partnerships are most robust in Amazonia and Cerrado. Mata Atlântica and Coastal maritime appear through complementary water, restoration and coastal linked initiatives. | L32: Strategic partner, Project developer / Implementer | M32: Upstream | N32: Grant recipient | O32: Arlington, VA, USA | P32: Grantee | T32: —
B33: 27 | C33: Conservação Internacional Brasil (CI-Brasil) | D33: Civil Society Organization (CSO) | E33: Local implementers | F33: A conservation NGO that works with nature-based solutions, science, and partnerships to protect biodiversity and promote human well-being; it operates through field projects, policy work, and coalitions. | G33: Cross-border / international | H33: "Land, Food and Forest" | I33: Amazonia, Cerrado | J33: Mata&Atlântica, Coastal&maritime | K33: Multi biome conservation portfolio with recurring emphasis on Amazonia and Cerrado. Mata Atlântica and Coastal maritime show up through specific projects and themes rather than being the main program anchors. | L33: Strategic partner, Project developer / Implementer | M33: Upstream | N33: Grant recipient | O33: Arlington, VA, USA | P33: Grantee | T33: —
B34: 28 | C34: WWF-Brasil | D34: Civil Society Organization (CSO) | E34: Local implementers | F34: A Brazilian NGO dedicated to conserving life and promoting a future in which society and nature live in harmony; it contributes through advocacy, projects, social mobilization, and influence on supply chains and public policy. | G34: Cross-border / international | H34: "Land, Food and Forest" | I34: Amazonia, Cerrado | J34: Pantanal, Mata&Atlântica | K34: High visibility campaigns and projects frequently center on Amazonia and Cerrado. Pantanal and Mata Atlântica remain relevant through water, biodiversity and climate risk agendas in a secondary layer. | L34: Strategic partner, Project developer / Implementer, Policy influence / regulation | M34: Midstream | N34: Grant recipient | O34: Brasília, DF, Brazil | P34: Grantee | T34: —
B35: 29 | C35: WRI Brasil | D35: Civil Society Organization (CSO) | E35: Monitoring, Evaluation, and Learning | F35: A non-profit applied research and convening institution that turns evidence into action on climate, forests, cities, and land use; it supports public policy, planning, and implementation of low-carbon solutions through multi-stakeholder partnerships. | G35: Cross-border / international | H35: Buildings & Transport, Energy, "Land, Food and Forest" | I35: Amazonia, Caatinga, Cerrado | J35: Mata&Atlântica | K35: Evidence to action work often focuses on land use and transition challenges most salient in Amazonia, Cerrado and Caatinga. Mata Atlântica appears through cities, infrastructure and policy work that intersects that biome footprint. | L35: Strategic partner, Technical assistance / research, Policy influence / regulation | M35: Upstream | N35: Grant recipient | O35: São Paulo, SP, Brazil | P35: Grantee | T35: Evidence-based research, data platforms and evaluation of climate and land-use policies
B36: 30 | C36: Fundação SOS Mata Atlântica | D36: Funders | E36: Monitoring, Evaluation, and Learning | F36: A Brazilian environmental NGO whose mission is to inspire society to defend the Atlantic Forest; it works through monitoring, studies, demonstration projects, communication, and advocacy in public policy and territorial governance. | G36: National | H36: "Land, Food and Forest" | J36: Mata&Atlântica | K36: Mission, monitoring and advocacy are explicitly dedicated to Mata Atlântica. This single biome focus is consistent across programs and public positioning. | L36: Policy influence / regulation, Implementation capacity (delivery) | M36: Midstream | N36: Grant recipient | O36: São Paulo, SP, Brazil | P36: Grantee | T36: Environmental monitoring of Atlantic Forest; deforestation tracking and advocacy indicators
B37: 31 | C37: Empresa Brasileira de Pesquisa Agropecuária (Embrapa) | D37: Public sector | E37: Research centers | F37: A federal public company for agricultural R&D; it contributes to systemic transition through innovation and technology diffusion for sustainable agriculture, climate adaptation, productivity, and reduced environmental impacts. | G37: National | H37: "Land, Food and Forest" | I37: Amazonia, Caatinga, Cerrado | J37: Mata&Atlântica, Pantanal, Pampa, Coastal&maritime | K37: National agricultural research network with core innovation and adaptation agendas strongly present in Cerrado, Caatinga and Amazonia. Other biomes are covered institutionally but are less central in the most recurrent transition narratives. | L37: Technical assistance / research, Territorial anchor | M37: Upstream | N37: Strategic partner | O37: Brasília, DF, Brazil | P37: Grantee | T37: —
B38: 32 | C38: Sistema S | D38: Others | E38: Industry platforms and sectoral initiatives | F38: A set of entities providing vocational training and public-interest services (e.g., SENAI, SESI, SESC, SENAC, etc.) financed through sectoral contributions; it contributes to the transition through training, reskilling, and innovation for work and productivity in strategic sectors. | G38: National | H38: Buildings & Transport, Energy | K38: Delivery model is based on training networks, sectoral services and local units. Programs are not defined by biomes, so biome tagging is not operationally meaningful. | L38: Implementation capacity (delivery), Technical assistance / research | M38: Midstream | N38: Strategic partner | O38: Brasília, DF, Brazil | P38: Grantee | T38: —
B39: 33 | C39: Instituto Brasileiro do Meio Ambiente e dos Recursos Naturais Renováveis (Ibama) | D39: Public sector | E39: Public agencies and regulators | F39: A federal agency responsible for environmental enforcement and control; it contributes to systemic transition through regulation, licensing, monitoring, combating environmental crimes, and inducing socio-environmental compliance. | G39: National | H39: Energy, "Land, Food and Forest" | I39: Amazonia, Caatinga, Cerrado | J39: Mata&Atlântica, Pantanal, Pampa, Coastal&maritime | K39: National enforcement and licensing mandate covers all biomes, but pressure hotspots make Amazonia, Cerrado and Caatinga the most recurrent references. Remaining biomes are still within scope, yet not a distinctive program delimitation. | L39: Policy influence / regulation, Territorial anchor | M39: Upstream | N39: Strategic partner | O39: Brasília, DF, Brazil | P39: Grantee | T39: —
B40: 34 | C40: Instituto Chico Mendes de Conservação da Biodiversidade (ICMBio) | D40: Public sector | E40: Public agencies and regulators | F40: A federal agency responsible for managing and overseeing federal protected areas; it contributes through biodiversity protection, restoration, protected-area management, and implementation of conservation policies. | G40: National | H40: "Land, Food and Forest" | I40: Amazonia, Caatinga, Cerrado | J40: Mata&Atlântica, Pantanal, Pampa, Coastal&maritime | K40: Manages federal protected areas across all biomes by mandate. The primary tags reflect where protected area scale and conflict pressures are most pronounced, while other biomes remain part of nationwide coverage. | L40: Policy influence / regulation, Territorial anchor | M40: Upstream | N40: Strategic partner | O40: Brasília, DF, Brazil | P40: Grantee | T40: —
B41: 35 | C41: Instituto do Homem e Meio Ambiente da Amazônia (Imazon) | D41: Civil Society Organization (CSO) | E41: Monitoring, Evaluation, and Learning | F41: A non-profit scientific institution that produces research and solutions for forest conservation and socio-environmental development in the Amazon; it works with data, monitoring, policy evaluation, and projects. | G41: Regional | H41: "Land, Food and Forest" | I41: Amazonia | K41: Research and monitoring are explicitly focused on Amazonia forest dynamics and governance. There is no recurring second biome portfolio line in the institute core work. | L41: Technical assistance / research, Data / MRV / platforms | M41: Upstream | N41: Grant recipient | O41: Belém, PA, Brazil | P41: Grantee | T41: Amazon deforestation monitoring, MRV data systems and policy evaluation (PRODES/SAD)
B42: 36 | C42: Fundação Amazonas Sustentável (FAS) | D42: Funders | E42: Local implementers | F42: A non-profit civil society organization working for sustainable development in the Amazon through community programs and multi-stakeholder partnerships; it contributes to the transition through conservation combined with productive inclusion and territorial strengthening. | G42: State-level | H42: "Land, Food and Forest" | I42: Amazonia | K42: Community based conservation and livelihoods programs are designed for Amazonia territories. Territorial focus is stable and central to the operating model. | L42: Project developer / Implementer, Territorial anchor | M42: Midstream | N42: Grant recipient | O42: Manaus, AM, Brazil | P42: Grantee | T42: —
B43: 37 | C43: Instituto de Manejo e Certificação Florestal e Agrícola (Imaflora) | D43: Civil Society Organization (CSO) | E43: Monitoring, Evaluation, and Learning | F43: A non-profit civil association that promotes change in the agricultural and forestry sectors; it works with certifications, technical assistance, projects, and market/policy mechanisms for sustainable land use and emissions reduction. | G43: National | H43: "Land, Food and Forest" | I43: Amazonia, Caatinga, Cerrado | J43: Mata&Atlântica, Pampa | K43: Certification and technical assistance in forest and agricultural supply chains are most recurrent in Amazonia and Cerrado, with added relevance in Caatinga through land use and production systems. Mata Atlântica and Pampa appear through specific chains and operating footprints. | L43: Technical assistance / research, Data / MRV / platforms | M43: Upstream | N43: Grant recipient | O43: Piracicaba, SP, Brazil | P43: Grantee | T43: Carbon monitoring, socio-environmental certification and MRV for agricultural/forest supply chains
B44: 38 | C44: Fundação Roberto Marinho | D44: Funders | E44: Philanthropy foundations | F44: A private foundation that runs projects in education, culture, heritage, and the environment; it contributes to the transition through educational innovation, communication/engagement, and capacity building for sustainable development. | G44: National | H44: Buildings & Transport, "Land, Food and Forest" | K44: Portfolio is broad and partnership driven across education and culture, with variable environmental projects. No stable biome based program boundary is consistently identifiable from this entry. | L44: Convenor/enablers, Implementation capacity (delivery) | M44: Midstream | N44: Strategic partner | O44: Rio de Janeiro, RJ, Brazil | P44: Re-granter | Q44: João Alegria (CEO) | R44: https://www.frm.org.br/ | S44: Could be a relevant partner to work on capacity building of vulnerable communities in Brazil. They Work in the whole country. Great capilarity | T44: —
B45: 39 | C45: Instituto de Pesquisa Econômica Aplicada (Ipea) | D45: Public sector | E45: Monitoring, Evaluation, and Learning | F45: A federal public research foundation that provides technical support for the formulation and evaluation of public policies; it contributes through evidence, indicators, and economic analysis to design and improve transition and development agendas. | G45: National | K45: Produces national policy research, indicators and evaluation with sector based framing. Biomes are not used as the primary unit to organize outputs or operations. | L45: Technical assistance / research, Policy influence / regulation | M45: Upstream | N45: Strategic partner | O45: Brasília, DF, Brazil | P45: Grantee | T45: Public policy evaluation, socioeconomic indicators and evidence for low-carbon transitions
B46: 40 | C46: Escola Nacional de Administração Pública (ENAP) | D46: Public sector | E46: Public agencies and regulators | F46: Federal school of government that trains civil servants, promotes innovation in public management, and strengthens state capacity for policy design, implementation, and evaluation. | G46: National | K46: Civil service training and innovation in public management are national and institution focused. Territorial framing follows government levels, not biome ecosystems. | L46: Technical assistance / research, Policy influence / regulation | M46: Upstream | N46: Strategic partner | O46: Brasília, DF, Brazil | P46: Grantee | T46: —
B47: 41 | C47: Instituto Serzedello Corrêa (ISC/TCU) | D47: Public sector | E47: Public agencies and regulators | F47: TCU’s training and knowledge institute focused on improving public governance, accountability, integrity, and oversight through education, research, and dissemination of best practices. | G47: National | H47: Buildings & Transport, Energy, "Land, Food and Forest" | K47: Strengthens governance and oversight through training and knowledge products. Work is transversal and not organized as place based biome initiatives. | L47: Technical assistance / research, Policy influence / regulation | M47: Upstream | N47: Strategic partner | O47: Brasília, DF, Brazil | P47: Grantee | T47: —
B48: 42 | C48: Vale S.A. | D48: Private sector | E48: Private companies (large / leading) | F48: Global mining company; can influence systemic transition through responsible mining, decarbonization targets, supply-chain standards, territorial development investments, and stronger ESG governance. | G48: Cross-border / international | H48: Buildings & Transport, Energy, "Land, Food and Forest" | I48: Amazonia, Cerrado | J48: Mata&Atlântica | K48: Operational presence and risk exposure are significant in Amazonia and Cerrado, with additional material interfaces in Mata Atlântica states. Biome tagging reflects where footprint and supply chain dynamics concentrate. | L48: Strategic partner, Implementation capacity (delivery) | M48: Downstream | N48: Co-funding partner | O48: Rio de Janeiro, RJ, Brazil | P48: Donor | T48: —
B49: 43 | C49: Suzano S.A. | D49: Private sector | E49: Private companies (large / leading) | F49: Leading pulp and paper company; contributes via sustainable forestry, restoration and bioeconomy pathways, low-carbon product innovation, and responsible value chains. | G49: Cross-border / international | H49: Energy, "Land, Food and Forest" | I49: Amazonia, Cerrado | J49: Mata&Atlântica | K49: Forestry and industrial landscapes connect strongly to Cerrado and Amazonia, with a sustained linkage to Mata Atlântica domains through assets and restoration agendas. The tags follow managed landscape concentration and reporting focus. | L49: Strategic partner, Implementation capacity (delivery) | M49: Downstream | N49: Co-funding partner | O49: São Paulo, SP, Brazil | P49: Donor | T49: —
B50: 44 | C50: Banco da Amazônia S.A. (BASA) | D50: Public sector | E50: Development banks | F50: Federal regional development bank focused on the Amazon; mobilizes credit and financial instruments for sustainable development, bioeconomy value chains, productive inclusion, and low-carbon land-use solutions. | G50: Regional | H50: Energy, "Land, Food and Forest" | I50: Amazonia | K50: Institutional mandate and financial instruments are oriented to Amazonia development and bioeconomy. This creates a clear single biome anchor for territorial focus. | L50: Capital provider / Financial intermediary, Territorial anchor | M50: Midstream | N50: Co-funding partner | O50: Belém, PA, Brazil | P50: Re-granter | T50: —
B51: 45 | C51: Instituto de Conservação e Desenvolvimento Sustentável da Amazônia (IDESAM) | D51: Civil Society Organization (CSO) | E51: Local implementers | F51: Amazon-based NGO advancing conservation and sustainable development through territorial projects, sustainable value chains, and climate solutions (including finance mechanisms where applicable). | G51: National | H51: "Land, Food and Forest" | I51: Amazonia | K51: Projects and value chains are consistently rooted in Amazonia territories and forest positive development. The organization identity and program design are explicitly Amazon focused. | L51: Project developer / Implementer, Technical assistance / research | M51: Downstream | N51: Grant recipient | O51: Manaus, AM, Brazil | P51: Grantee | Q51: Paola Bleicker (Executive Director) | R51: https://idesam.org/ | S51: Relevant SIB partner in the Amazon. | T51: —
B52: 46 | C52: Sitawi Finanças do Bem | D52: Civil Society Organization (CSO) | E52: Impact investors | F52: Nonprofit that structures and manages impact finance mechanisms (e.g., funds, blended finance, governance of philanthropic/impact resources), connecting capital to measurable socio-environmental outcomes. | G52: National | H52: Buildings & Transport, Energy, "Land, Food and Forest" | K52: Structures impact finance and governance mechanisms across themes and sectors. Geographic reach depends on deals and partners, so no stable biome specific allocation logic is evident. | L52: Capital provider / Financial intermediary, Project developer / Implementer | M52: Midstream | N52: Grant recipient | O52: São Paulo, SP, Brazil | P52: Re-granter | T52: —
B53: 47 | C53: Din4mo | D53: Private sector | E53: Impact investors | F53: Impact investor/venture builder that mobilizes capital and supports impact ventures with strategy and investment, helping scale solutions aligned with inclusive and low-carbon development. | G53: National | H53: Buildings & Transport, Energy, "Land, Food and Forest" | K53: Invests and builds ventures by impact thesis and market opportunity across Brazil. Portfolio is not disclosed as a biome delimited strategy. | L53: Capital provider / Financial intermediary | M53: Midstream | N53: Grant recipient | O53: São Paulo, SP, Brazil | P53: Re-granter | T53: —
B54: 48 | C54: Artemisia | D54: Civil Society Organization (CSO) | E54: Local implementers | F54: Nonprofit accelerator and ecosystem builder for impact businesses in Brazil; strengthens entrepreneurs and scalable models that address inequality and socio-environmental challenges. | G54: National | H54: Buildings & Transport | K54: Accelerates impact businesses through programs and networks, mostly organized by target population and business model. It does not consistently categorize its work by biome. | L54: Convenor/enablers, Implementation capacity (delivery) | M54: Midstream | N54: Grant recipient | O54: São Paulo, SP, Brazil | P54: Grantee | Q54: Priscila Martins (Co-Director) | R54: https://artemisia.org.br/ | S54: Great partner to implement SIB strategies in Brazil. | T54: —
B55: 49 | C55: Instituto de Cidadania Empresarial (ICE) | D55: Civil Society Organization (CSO) | E55: Think tanks | F55: Civil society organization that convenes business leaders and partners to foster corporate citizenship, social innovation, and multi-stakeholder collaboration for systemic change. | G55: National | K55: Convening and corporate citizenship work is agenda and network driven. It is not implemented through territorially bounded biome programs. | L55: Convenor/enablers, Technical assistance / research | M55: Upstream | N55: Grant recipient | O55: São Paulo, SP, Brazil | P55: Grantee | Q55: Carla Duprat (Execiutive Director) | R55: https://ice.org.br/ | S55: Relevant partner in the SIB arena in Brazil. | T55: —
B56: 50 | C56: Impact Hub Network | D56: Private sector | E56: Multi-stakeholder initiatives | F56: Global network of impact innovation hubs (coworking + programs) that supports entrepreneurship, collaboration, and the scaling of socio-environmental solutions. | G56: Cross-border / international | H56: Buildings & Transport, Energy, "Land, Food and Forest" | K56: Global innovation hub network with local ecosystem programming. Biomes are not used as the unit of action, since operations are city and community based. | L56: Convenor/enablers, Implementation capacity (delivery) | M56: Midstream | N56: Grant recipient | O56: Vienna, Austria | P56: Grantee | T56: —
B57: 51 | C57: Instituto Conexões Sustentáveis (Conexsus) | D57: Civil Society Organization (CSO) | E57: Local implementers | F57: Nonprofit that accelerates sustainable community-based enterprises, connecting cooperatives/associations to markets and finance to strengthen territorial resilience and the low-carbon transition. | G57: National | H57: "Land, Food and Forest" | I57: Amazonia, Caatinga, Cerrado | J57: Mata&Atlântica, Pampa | K57: Community enterprise acceleration is strongly present in Amazonia, Cerrado and Caatinga through socio biodiversity value chains and territorial businesses. Mata Atlântica and Pampa appear as secondary through additional regional networks and projects. | L57: Capital provider / Financial intermediary, Implementation capacity (delivery) | M57: Midstream | N57: Grant recipient | O57: São Paulo, SP, Brazil | P57: Re-granter | Q57: Fabíola Zerbini (Executive Director) | R57: https://www.conexsus.org/ | S57: Relevant implementing partner for SIB in the Amazon. | T57: —
B58: 52 | C58: Pipe.Social | D58: Private sector | E58: Multi-stakeholder initiatives | F58: Platform that maps and connects impact businesses with investors, corporations, and partners; facilitates matchmaking and programs to scale impact solutions. | G58: National | H58: Buildings & Transport, Energy, "Land, Food and Forest" | K58: Matchmaking platform for impact ventures and investors, organized by sectors and portfolios. No consistent biome delimited implementation layer is observable. | L58: Data / MRV / platforms, Convenor/enablers | M58: Upstream | N58: Blended finance partner | O58: São Paulo, SP, Brazil | P58: Grantee | Q58: Mariana Fonseca (Director) | R58: https://pipe.social/ | S58: Relevant SIB finance plataform. | T58: —
B59: 53 | C59: Yunus Negócios Sociais (Brasil) | D59: Private sector | E59: Impact investors | F59: Organization that supports and finances social businesses, connecting entrepreneurs to capital, networks, and corporate innovation to scale solutions that reduce inequality and generate socio-environmental impact. | G59: National | H59: Buildings & Transport, Energy, "Land, Food and Forest" | K59: Supports social businesses via investment readiness, capital and partnerships. The territorial footprint is opportunity driven and not structured by biomes as a program boundary. | L59: Capital provider / Financial intermediary, Implementation capacity (delivery) | M59: Midstream | N59: Co-funding partner | O59: Wiesbaden, Germany | P59: Re-granter | Q59: Walter Campos is the General Manager | R59: https://yunusns.com/ | S59: Strategic and potential partner for SIB in Brazil. | T59: —
B60: 54 | C60: Instituto C&A | D60: Civil Society Organization (CSO) | E60: Philanthropy foundations | F60: C&A’s social investment institute in Brazil; mobilizes partners and programs to strengthen communities through inclusion and opportunity pathways, supporting broader equitable development. | G60: National | H60: Buildings & Transport, "Land, Food and Forest" | K60: Corporate social investment focused on inclusion and opportunities, implemented through partners and programs. It does not present a consistent biome targeted approach in this mapping. | L60: Funder, Strategic partner | M60: Upstream | O60: Barueri, SP, Brazil | P60: Donor | T60: —
B61: 55 | C61: Lundin Foundation | D61: Funders | E61: Philanthropy foundations | F61: Nonprofit foundation that supports inclusive economic development and community benefit initiatives, often in partnership with local stakeholders and the private sector. | G61: Cross-border / international | H61: "Land, Food and Forest" | K61: International foundation with broad inclusive development work. This entry does not provide a stable Brazil facing biome structured program set to classify. | L61: Funder, Strategic partner | M61: Upstream | N61: Co-funding partner | O61: Vancouver, BC, Canada | P61: Donor | R61: https://www.lundinfoundation.org/ | T61: —
B62: 56 | C62: Aliança Empreendedora | D62: Civil Society Organization (CSO) | E62: Local implementers | F62: NGO that supports micro and small entrepreneurs in vulnerable contexts through training, networks, and market access—strengthening inclusive local economies and productive inclusion. | G62: National | K62: Works with micro and small entrepreneurs through training and market access in vulnerable contexts. Territorial reach is defined by communities and cities, not by biome ecosystems. | L62: Implementation capacity (delivery) | M62: Downstream | N62: Co-funding partner | O62: Curitiba, PR, Brazil | P62: Grantee | Q62: Carolina Borghesi (VP) | R62: https://institutocea.org.br/ | S62: Could be an important co-funding parter in assignes supply chain for IKF targeted geographies. | T62: —
B63: 57 | C63: Omidyar Network | D63: Funders | E63: Philanthropy foundations | F63: Philanthropic investment organization combining grants and investments to expand shared prosperity and opportunity, often backing initiatives that strengthen inclusion, institutions, and responsible technology. | G63: Cross-border / international | K63: Combines grants and investments globally to expand inclusion and strong institutions. In this dataset, a consistent Brazil biome based segmentation is not documented for classification. | L63: Funder, Strategic partner | M63: Upstream | N63: Co-funding partner | O63: Redwood City, CA, USA | P63: Donor | T63: —
B64: 58 | C64: Fundação Grupo Boticário de Proteção à Natureza | D64: Funders | E64: Philanthropy foundations | F64: Nonprofit foundation maintained by the Boticário Group that funds and advances biodiversity conservation, protected areas, restoration, and nature-positive agendas (including water security and regenerative economy pathways). | G64: National | H64: Buildings & Transport, "Land, Food and Forest" | I64: Cerrado | J64: Mata&Atlântica | K64: Flagship conservation and restoration initiatives maintain clear linkages to Cerrado and Mata Atlântica. The tags reflect where long term reserves, partnerships and public programs are most explicitly concentrated. | L64: Funder, Project developer / Implementer | M64: Upstream | N64: Co-funding partner | O64: Curitiba, PR, Brazil | P64: Donor | Q64: Malu Nunes (Executive Director) | R64: https://fundacaogrupoboticario.org.br/ | S64: Could be an important co-funding partenr for IKF in Brazil. | T64: —
B65: 59 | C65: Natura | D65: Private sector | E65: Private companies (large / leading) | F65: Consumer goods company with strong commitments to sustainability; can drive systemic transition through responsible sourcing (including sociobiodiversity), circular economy practices, low-carbon innovation, and influence across value chains. | G65: National | H65: "Land, Food and Forest" | I65: Amazonia, Cerrado | J65: Mata&Atlântica, Pampa, Pantanal | K65: Sociobiodiversity sourcing and forest positive supply chains create a strong anchor in Amazonia, with important interfaces in Cerrado. Other biomes are part of corporate reach, but are less consistently presented as core territorial program lines. | L65: Strategic partner, Implementation capacity (delivery) | M65: Downstream | N65: Co-funding partner | O65: Cajamar, SP, Brazil | P65: Donor | R65: https://www.natura.com.br/ | S65: Could be an important co-funding partenr for IKF in Brazil. | T65: —
B66: 60 | C66: Programa das Nações Unidas para o Desenvolvimento (PNUD) | D66: Others | E66: Multilateral organizations | F66: UN development agency that provides technical cooperation, program implementation support, and policy assistance aligned with the SDGs (governance, inclusion, poverty reduction, and climate resilience). | G66: Cross-border / international | H66: Buildings & Transport, Emergency response, Energy, "Land, Food and Forest" | K66: Cooperation is organized by SDG programs and government counterparts, with implementation varying by project. This entry does not show a stable biome specific portfolio structure to apply systematically. | L66: Strategic partner, Convenor/enablers, Project developer / Implementer | M66: Midstream | N66: Strategic partner | O66: New York, NY, USA | P66: Re-granter | Q66: Luciana Aguiar (Country Program Director) | R66: https://www.undp.org/pt/brazil | S66: Strategic partner for IKF impact areas and biomes. | T66: —
B67: 61 | C67: Centro de Empreendedorismo da Amazônia (CEA) | D67: Others | E67: Local implementers | F67: Platform that strengthens entrepreneurship and the bioeconomy in the Amazon by offering capacity building, ecosystem convening, and connections to markets and investors for sustainable businesses. | G67: Regional | H67: "Land, Food and Forest" | I67: Amazonia | K67: It operated explicitly as an Amazon-region platform and delivered bioeconomy/entrepreneurship support anchored in Amazonia. | L67: Technical assistance / research, Implementation capacity (delivery) | M67: Midstream | N67: Grant recipient | O67: Belém, PA, Brazil | P67: Grantee | Q67: Raphael Medeiros (Executive Director) | R67: https://centroamazonia.org.br/ | S67: Relevant implementing org addressing SIB in the Amazon. | T67: —
B68: 62 | C68: Manioca | D68: Private sector | E68: Private companies (SMEs / local enterprises) | F68: Impact-oriented food brand that works with Amazon-linked supply chains; contributes through fairer sourcing, product innovation, and strengthening local producers and sustainable value chains. | G68: Regional | H68: "Land, Food and Forest" | I68: Amazonia | K68: It used Amazon-linked supply chains and supported producers connected to the Amazonia biome. | L68: Implementation capacity (delivery) | M68: Downstream | N68: Grant recipient | O68: São Paulo, SP, Brazil | P68: Grantee | R68: https://sistemabbrasil.org/empresas-b | S68: Could be a potential grantee in the food arean in the Amazon (Pará State). | T68: —
B69: 63 | C69: Instituto Votorantim | D69: Civil Society Organization (CSO) | E69: Philanthropy foundations | F69: Corporate institute that acts as an applied intelligence and partnership platform, supporting socio-environmental solutions, territorial development, and better corporate practices for sustainability. | G69: National | H69: Buildings & Transport, Energy, "Land, Food and Forest" | K69: It operated through corporate social investment and partnerships and did not maintain a public biome-specific program cut. | L69: Funder, Strategic partner | M69: Upstream | N69: Co-funding partner | O69: São Paulo, SP, Brazil | P69: Donor | Q69: Rafael Gioielli (Executive Director) | R69: https://www.institutovotorantim.org.br/ | S69: Important co-funding partner on tge SIB in Brazil. Track reccord on funding in the northeast of the country. | T69: —
B70: 64 | C70: Quintessa | D70: Private sector | E70: Impact investors | F70: Impact accelerator/consultancy that supports impact ventures with mentoring, strategy and investment readiness, connecting entrepreneurs to capital and partners to scale solutions. | G70: National | H70: Buildings & Transport, Energy, "Land, Food and Forest" | K70: It accelerated ventures across themes and did not classify its programs by biome. | L70: Implementation capacity (delivery), Convenor/enablers | M70: Midstream | N70: Grant recipient | O70: São Paulo, SP, Brazil | P70: Grantee | Q70: Nana Baffour (Director) | R70: https://www.quintessa.org.br/ | S70: Relevant SIB plataform of investments. | T70: —
B71: 65 | C71: De Mendes | D71: Private sector | E71: Private companies (SMEs / local enterprises) | F71: Local enterprise linked to sustainable value chains (e.g., cacao/chocolate); can contribute via responsible sourcing, territorial development, and inclusive value creation with producers. | G71: State-level | H71: "Land, Food and Forest" | I71: Amazonia | K71: It was linked to value chains at state level, but no clear public evidence of biome-targeted initiatives was identified in this mapping. | L71: Implementation capacity (delivery) | M71: Downstream | N71: Grant recipient | O71: Ilhéus, BA, Brazil | P71: Grantee | R71: https://www.demendes.com.br/ | S71: could be a potential grantee in the food - cocoa supply chain in Brazil. | T71: —
B72: 66 | C72: Endeva | D72: Civil Society Organization (CSO) | E72: Think tanks | F72: System-innovation and inclusive-business organization working with companies, governments, and civil society to design scalable solutions, strengthen inclusive value chains, and generate evidence for systemic change. | G72: Cross-border / international | H72: "Land, Food and Forest" | K72: It worked on inclusive business/system innovation across sectors and did not use Brazilian biomes as a standard program boundary. | L72: Technical assistance / research | M72: Upstream | N72: Grant recipient | O72: Berlin, Germany | P72: Grantee | T72: —
B73: 67 | C73: Insper | D73: Civil Society Organization (CSO) | E73: Academia | F73: Higher education and research institution that trains leaders and produces applied knowledge in economics, business and public policy, supporting evidence-based decisions for sustainability transitions. | G73: State-level | K73: It operated as an academic institution and did not present biome-defined projects as a primary organizing lens in this list. | L73: Technical assistance / research | M73: Upstream | N73: Strategic partner | O73: São Paulo, SP, Brazil | P73: Grantee | R73: https://www.insper.edu.br/pt | S73: Great plavce to explore data assessment on a range of IFK impact areas and biomes in Brazil. | T73: —
B74: 68 | C74: Positive Ventures | D74: Private sector | E74: Impact investors | F74: Impact venture capital investor supporting startups with measurable social/environmental outcomes, accelerating innovation and scaling solutions for inclusive and low-carbon transitions. | G74: National | H74: Buildings & Transport, "Land, Food and Forest" | K74: A venture capital firm that invests in early-stage startups committed to generating positive and measurable social and environmental impact. | L74: Capital provider / Financial intermediary | M74: Midstream | N74: Grant recipient | O74: São Paulo, SP, Brazil | P74: Re-granter | T74: —
B75: 69 | C75: BMW Foundation Herbert Quandt | D75: Funders | E75: Philanthropy foundations | F75: Foundation that supports responsible leadership and social innovation, convening cross-sector networks and programs to address complex societal challenges. | G75: Cross-border / international | K75: It ran leadership and social innovation programs internationally and did not provide a Brazil-biome-specific portfolio cut. | L75: Funder, Convenor/enablers | M75: Upstream | N75: Co-funding partner | O75: Munich, Germany | P75: Donor | Q75: Sandra Ortiz (Latin America Director) | R75: https://www.bmw-foundation.org/ | S75: A strategic co-funding partner on ecossystem transformation, using SIB as a key element to get there. | T75: —
B76: 70 | C76: Ford Foundation | D76: Funders | E76: Philanthropy foundations | F76: Global philanthropic foundation focused on social justice and reducing inequality; supports organizations and systemic agendas, including intersections with climate justice and rights. | G76: Cross-border / international | H76: "Land, Food and Forest" | K76: It funded broad social-justice agendas and did not define a consistent Brazil-biome program cut for this dataset. | L76: Funder, Strategic partner | M76: Upstream | N76: Co-funding partner | O76: New York, NY, USA | P76: Donor | Q76: Atila Rock (Brazil Country Director) | R76: https://www.fordfoundation.org/our-work-around-the-world/brazil-pt/ | S76: Key partner to address climate change funding in the Amazon, specially on the forest and community based approaches. | T76: —
B77: 71 | C77: Instituto Sabin | D77: Civil Society Organization (CSO) | E77: Philanthropy foundations | F77: Corporate social investment institute linked to Grupo Sabin; supports initiatives and partnerships (commonly in health, education and community development) that build local capacities and inclusion. | G77: National | K77: It focused on health/education/community partnerships and did not operate with a biome-based territorial strategy. | L77: Funder, Territorial anchor | M77: Upstream | N77: Co-funding partner | O77: Brasília, DF, Brazil | P77: Donor | Q77: Raquel Ribeiro Vaz (President) | R77: https://institutosabin.org.br/ | S77: Could be a partner to co-fund a portfolio of projects in targeted cities (co-benefit agenda) | T77: —
B78: 72 | C78: Instituto Phi | D78: Civil Society Organization (CSO) | E78: Philanthropy foundations | F78: Philanthropy organization that mobilizes donors and structures giving toward high-impact projects, strengthening the Brazilian giving ecosystem and scaling effective initiatives. | G78: National | H78: Buildings & Transport, Energy, "Land, Food and Forest" | K78: It mobilized donors and structured giving nationally and did not target interventions using biome boundaries. | L78: Project developer / Implementer, Convenor/enablers, Implementation capacity (delivery) | M78: Midstream | N78: Grant recipient | O78: Rio de Janeiro, RJ, Brazil | P78: Grantee | Q78: Luíza Serpa (Executive Director) | R78: Instituto Phi | S78: A relevant potential regreting organizatio to addres international Foundation work in Brazil. Track reccord doing that (LATIMPACTO, among others). | T78: —
B79: 73 | C79: Deloitte | D79: Private sector | E79: Private companies (large / leading) | F79: Professional services firm that can support transitions through ESG strategy, governance, risk management, compliance, measurement, and implementation support for organizations. | G79: Cross-border / international | K79: It provided advisory services across sectors and geographies and did not apply a biome-specific delivery model. | L79: Technical assistance / research, Data / MRV / platforms | M79: Upstream | N79: Co-funding partner | O79: London, United Kingdom | P79: Donor | T79: —
B80: 74 | C80: Centro de Estudos em Sustentabilidade da FGV (FGVces) | D80: Funders | E80: Monitoring, Evaluation, and Learning | F80: Applied sustainability research center that develops methods, metrics and convening to inform corporate strategies and public policies for low-carbon and inclusive transitions. | G80: National | H80: Buildings & Transport, Emergency response, Energy, "Land, Food and Forest" | K80: It produced applied research and convening and did not define its work through biome-specific implementation portfolios. | L80: Technical assistance / research, Data / MRV / platforms | M80: Upstream | N80: Grant recipient | O80: São Paulo, SP, Brazil | P80: Grantee | S80: Could be a research parner for IKF in Brazil. | T80: Impact measurement methodology, corporate sustainability metrics and climate policy evaluation
B81: 75 | C81: Fundação Dom Cabral (FDC) | D81: Funders | E81: Academia | F81: Business school providing executive education and applied research; strengthens leadership, governance and organizational capabilities for sustainability and systemic transformation. | G81: National | K81: It delivered executive education and applied research and did not organize activities through biome-based cuts. | L81: Technical assistance / research | M81: Upstream | N81: Grant recipient | O81: Nova Lima, MG, Brazil | P81: Grantee | S81: Could be a research parner for IKF in Brazil. | T81: —
B82: 76 | C82: Instituto Brasileiro de Governança Corporativa (IBGC) | D82: Civil Society Organization (CSO) | E82: Industry platforms and sectoral initiatives | F82: Reference institution for corporate governance in Brazil; disseminates standards and training that strengthen accountability, transparency and long-term value creation aligned with sustainability. | G82: National | K82: It disseminated governance standards and training nationally and did not use biomes as an operational lens. | L82: Policy influence / regulation, Convenor/enablers | M82: Upstream | N82: Grant recipient | O82: São Paulo, SP, Brazil | P82: Grantee | S82: Could be an important partner to advance governance in philanthropy in Brazil. | T82: —
B83: 77 | C83: Escola Superior de Agricultura Luiz de Queiroz da USP (ESALQ/USP) | D83: Public sector | E83: Academia | F83: USP school dedicated to teaching and research in agrifood systems and land use; contributes via innovation for sustainable agriculture, climate adaptation and bioeconomy. | G83: State-level | K83: It operated as an academic/research school and did not present a stable set of biome-targeted projects in this list. | L83: Technical assistance / research | M83: Upstream | N83: Grant recipient | O83: Piracicaba, SP, Brazil | P83: Grantee | S83: Could be an important partner to advance governance in philanthropy in Brazil. | T83: —
B84: 78 | C84: Bemtevi | D84: Private sector | E84: Private companies (SMEs / local enterprises) | F84: Impact-oriented organization/consultancy that supports strategy, partnerships and implementation of socio-environmental projects, helping scale solutions across territories and value chains. | G84: National | H84: Buildings & Transport, Energy, "Land, Food and Forest" | K84: It supported projects across territories and value chains, but no consistent biome-defined portfolio was identified in this mapping. | L84: Capital provider / Financial intermediary | M84: Midstream | N84: Co-funding partner | O84: São Paulo, SP, Brazil | P84: Re-granter | T84: —
B85: 79 | C85: Climate and Land Use Alliance (CLUA) | D85: Funders | E85: Alliances | F85: Alliance of philanthropic foundations that aligns strategies and funding to reduce deforestation, improve land-use governance, and advance climate and nature outcomes with social benefits. | G85: Cross-border / international | H85: "Land, Food and Forest" | I85: Amazonia, Cerrado | K85: It aligned funding to reduce deforestation with a clear emphasis on Amazonia and also supported land-use governance agendas linked to Cerrado. | L85: Funder, Strategic partner | M85: Upstream | N85: Co-funding partner | O85: San Francisco, CA, USA | P85: Donor | Q85: Atila Rock (FFoundation BRAZIL Country Director) | R85: https://climateandlandusealliance.org › ... | S85: Relkevant strategic and co-funding partner for IKF in Brazil in different arenas: biomes and impact areas. | T85: —
B86: 80 | C86: AMAZ | D86: Civil Society Organization (CSO) | E86: Impact investors | F86: Impact accelerator and investor focused on the Amazon region; supports impact enterprises that generate positive outcomes for forests and local populations, strengthening sustainable business models and access to finance/markets. | G86: Regional | H86: "Land, Food and Forest" | I86: Amazonia | K86: It focused its acceleration and investment mandate on the Amazon region, which anchored its work in Amazonia. | L86: Capital provider / Financial intermediary | M86: Midstream | N86: Grant recipient | O86: Manaus, AM, Brazil | P86: Re-granter | Q86: SIB "arm" in the Amazon, as a spin-off of IDESAM. Could be a fund holder for SIB in the Amazon. | T86: —
B87: 81 | C87: Mercado Livre | D87: Private sector | E87: Private companies (large / leading) | F87: Leading e-commerce and logistics company in Latin America; can influence systemic transition through low-carbon logistics, responsible packaging, supplier standards, and scaling access for SMEs and sustainable products. | G87: Cross-border / international | H87: Buildings & Transport | K87: It operated through regional logistics and platform services and did not define actions using Brazilian biome boundaries. | L87: Strategic partner, Implementation capacity (delivery) | M87: Downstream | N87: Co-funding partner | O87: Buenos Aires, Argentina | P87: Donor | T87: —
B88: 82 | C88: Amazon | D88: Private sector | E88: Private companies (large / leading) | F88: Global e-commerce, cloud and logistics company; can influence systemic transition via renewable energy procurement, low-carbon logistics, responsible supply chains, and scaling digital infrastructure for climate and inclusion solutions. | G88: Cross-border / international | H88: Buildings & Transport | K88: It ran global logistics/cloud operations and did not structure Brazil activities by biome in a way that was identifiable for this mapping. | L88: Strategic partner, Implementation capacity (delivery) | M88: Downstream | N88: Co-funding partner | O88: Seattle, WA, USA | P88: Donor | T88: —
B89: 83 | C89: CocoaAction Brasil | D89: Others | E89: Multi-stakeholder initiatives | F89: Pre-competitive public–private cocoa-sector platform that aligns companies, government and partners to advance sustainable, forest-positive cocoa production, improve farmer livelihoods, and strengthen responsible value chains. | G89: National | H89: "Land, Food and Forest" | I89: Amazonia | J89: Mata&Atlântica | K89: It supported cocoa value chains strongly linked to Bahia (Mata Atlântica) and also connected to Amazon-region cocoa expansion/production landscapes (Amazonia). | L89: Convenor/enablers, Project developer / Implementer | M89: Midstream | N89: Co-funding partner | O89: São Paulo, SP, Brazil | P89: Donor | T89: —
B90: 84 | C90: Instituto de Pesquisas Ecológicas (IPÊ) | D90: Civil Society Organization (CSO) | E90: Local implementers | F90: Brazilian NGO combining science, education and socio-environmental innovation to conserve biodiversity and support sustainable development across multiple biomes through community-based projects and policy-relevant evidence. | G90: National | H90: "Land, Food and Forest" | I90: Amazonia | J90: Mata&Atlântica, Pantanal | K90: It implemented flagship landscape conservation/restoration work in the Atlantic Forest and also maintained projects/partnerships linked to the Amazon region. | L90: Technical assistance / research, Project developer / Implementer | M90: Downstream | N90: Grant recipient | O90: Nazaré Paulista, SP, Brazil | P90: Grantee | T90: —
B91: 85 | C91: Comunitas | D91: Civil Society Organization (CSO) | E91: Multi-stakeholder initiatives | F91: Civil society hub/think tank that builds bridges between public and private leadership to strengthen state capacity, improve public management, and structure collaborative solutions for sustainable development. | G91: National | H91: Buildings & Transport, Energy, "Land, Food and Forest" | K91: It worked on state capacity and collaborative governance and did not use biomes as an implementation boundary. | L91: Convenor/enablers, Policy influence / regulation | M91: Midstream | N91: Grant recipient | O91: São Paulo, SP, Brazil | P91: Grantee | T91: —
B92: 86 | C92: Fundação Oswaldo Cruz (Fiocruz) | D92: Public sector | E92: Research centers | F92: Public research institution in health; contributes to systemic transition through science and innovation, public health systems strengthening, climate-and-health evidence, and applied knowledge for resilient and equitable development. | G92: National | H92: Emergency response, "Land, Food and Forest" | K92: It operated nationally in health research/policy and did not frame its core programs through biome-specific cuts. | L92: Technical assistance / research, Territorial anchor | M92: Upstream | N92: Strategic partner | O92: Rio de Janeiro, RJ, Brazil | P92: Grantee | T92: —
B93: 87 | C93: Universidade de Brasília (UnB) | D93: Public sector | E93: Academia | F93: Public university that contributes through research, teaching and policy engagement; supports systemic transition by generating evidence and training leaders for public policy, sustainability and innovation agendas. | G93: State-level | K93: It operated in the Cerrado territory and maintained research and outreach agendas strongly associated with Cerrado socio-environmental issues. | L93: Technical assistance / research | M93: Upstream | N93: Strategic partner | O93: Brasília, DF, Brazil | P93: Grantee | T93: —
B94: 88 | C94: Universidade Federal do Pará (UFPA) | D94: Public sector | E94: Academia | F94: Public university in the Amazon region; contributes via research and training on socio-biodiversity, territorial development, climate and governance, supporting evidence-based solutions in the region. | G94: State-level | K94: It was based in the Amazon region and delivered research/training linked to Amazonian socio-biodiversity and territorial development. | L94: Technical assistance / research, Territorial anchor | M94: Upstream | N94: Strategic partner | O94: Belém, PA, Brazil | P94: Grantee | T94: —
B95: 89 | C95: Universidade de São Paulo (USP) | D95: Public sector | E95: Academia | F95: Public university and major research institution; contributes to systemic transition through high-impact research, innovation, and training across climate, nature, health, and sustainable development fields. | G95: State-level | K95: It produced broad research and training and did not present a biome-targeted portfolio cut that could be consistently assigned here. | L95: Technical assistance / research | M95: Upstream | N95: Strategic partner | O95: São Paulo, SP, Brazil | P95: Grantee | T95: —
B96: 90 | C96: Fundação Nacional dos Povos Indígenas (FUNAI) | D96: Public sector | E96: Public agencies and regulators | F96: Federal agency responsible for Indigenous peoples’ rights and protection; influences systemic transition by safeguarding territories, supporting socio-environmental governance, and enabling rights-based approaches to land use and development. | G96: National | H96: "Land, Food and Forest" | I96: Amazonia, Caatinga, Cerrado | J96: Mata&Atlântica, Pantanal, Pampa, Coastal&maritime | K96: It held a nationwide mandate across Indigenous territories and did not operate through a single or stable biome-defined program boundary in this mapping. | L96: Policy influence / regulation, Territorial anchor | M96: Upstream | N96: Strategic partner | O96: Brasília, DF, Brazil | P96: Grantee | T96: —
B97: 91 | C97: Fundação Brasileira para o Desenvolvimento Sustentável (FBDS) | D97: Civil Society Organization (CSO) | E97: Think tanks | F97: Private non-profit foundation that generates knowledge and applied projects on sustainability; supports better policy and corporate practice through research, indicators and technical work on climate, land use and sustainable development. | G97: National | H97: Buildings & Transport, Energy, "Land, Food and Forest" | K97: It worked through applied studies and projects across themes and did not disclose a consistent biome-targeted portfolio. | L97: Technical assistance / research, Strategic partner | M97: Upstream | N97: Grant recipient | O97: Rio de Janeiro, RJ, Brazil | P97: Grantee | T97: —
B98: 92 | C98: Grupo Terra Nova | D98: Private sector | E98: Private companies (SMEs / local enterprises) | F98: Organization specialized in land tenure conflict mediation and regularization; contributes to systemic transition by enabling legal security, inclusive urban development, and negotiated solutions that reduce social conflict and strengthen territorial governance. | G98: National | H98: "Land, Food and Forest" | K98: It delivered mediation/regularization services across territories and did not define operations by biome. | L98: Implementation capacity (delivery) | M98: Downstream | N98: Co-funding partner | O98: São Paulo, SP, Brazil | P98: Grantee | T98: —
B99: 93 | C99: Grupo Aterpa | D99: Private sector | E99: Private companies (large / leading) | F99: Infrastructure and environmental engineering group (e.g., water and sanitation); can support systemic transition through universal sanitation delivery, resilient infrastructure, and improved environmental performance in project design and operation. | G99: National | H99: Buildings & Transport | K99: It implemented infrastructure projects by client/municipality and did not use biomes as an organizing lens. | L99: Implementation capacity (delivery) | M99: Downstream | N99: Co-funding partner | O99: Belo Horizonte, MG, Brazil | P99: Grantee | T99: —
B100: 94 | C100: Observatório do Clima | D100: Civil Society Organization (CSO) | E100: Monitoring, Evaluation, and Learning | F100: Civil society coalition created to address climate change in Brazil; produces analysis, monitoring and advocacy to strengthen climate governance, transparency and ambitious public policy. | G100: National | H100: Buildings & Transport, Energy, "Land, Food and Forest" | K100: It focused on national climate governance and policy advocacy and did not maintain a biome-specific implementation portfolio. | L100: Policy influence / regulation, Convenor/enablers | M100: Upstream | N100: Grant recipient | O100: Brasília, DF, Brazil | P100: Grantee | T100: GHG emissions monitoring (SEEG), annual sectoral data production and climate transparency
B101: 95 | C101: United States Agency for International Development (USAID) | D101: Public sector | E101: Bilateral cooperation agencies | F101: U.S. government development cooperation agency that provides funding, technical assistance, and partnerships to support international development priorities (e.g., governance, health, food security, climate resilience), helping scale solutions and strengthen institutions. | G101: Cross-border / international | H101: Buildings & Transport, Emergency response, Energy, "Land, Food and Forest" | K101: It funded multi-sector international cooperation and did not provide a stable Brazil-biome-specific cut in this mapping. | L101: Funder, Strategic partner | M101: Upstream | N101: Co-funding partner | O101: Washington, DC, USA | P101: Donor | S101: It was very relevant in the past funding for the Amazon in Brazil. | T101: —
B102: 96 | C102: Gordon and Betty Moore Foundation | D102: Funders | E102: Philanthropy foundations | F102: International grantmaking foundation that funds science and environmental conservation, supporting evidence-based approaches, ecosystem protection, and systemic solutions for climate and nature. | G102: Cross-border / international | H102: Energy, "Land, Food and Forest" | I102: Amazonia | K102: It funded global conservation/science agendas and did not present a consistent Brazil-biome segmentation in this dataset. | L102: Funder, Strategic partner | M102: Upstream | N102: Co-funding partner | O102: Palo Alto, CA, USA | P102: Donor | S102: One on the most relevant co-funding partner for the Amazon in Brazil. | T102: —
...

Sheet Data_Looker
A1: ='Stakeholder list'!B6 | B1: ='Stakeholder list'!C6 | C1: ='Stakeholder list'!D6 | D1: ='Stakeholder list'!E6 | E1: ='Stakeholder list'!F6 | F1: ='Stakeholder list'!G6 | G1: ='Stakeholder list'!H6 | H1: ='Stakeholder list'!I6 | ... R1: ='Stakeholder list'!S6
A2: ='Stakeholder list'!B7 | B2: ='Stakeholder list'!C7 | C2: ='Stakeholder list'!D7 | D2: ='Stakeholder list'!E7 | E2: ='Stakeholder list'!F7 | F2: ='Stakeholder list'!G7 | G2: ='Stakeholder list'!H7 | H2: ='Stakeholder list'!I7 | ... R2: ='Stakeholder list'!S7
A3: ='Stakeholder list'!B8 | B3: ='Stakeholder list'!C8 | C3: ='Stakeholder list'!D8 | D3: ='Stakeholder list'!E8 | E3: ='Stakeholder list'!F8 | F3: ='Stakeholder list'!G8 | G3: ='Stakeholder list'!H8 | H3: ='Stakeholder list'!I8 | ... R3: ='Stakeholder list'!S8
A4: ='Stakeholder list'!B9 | B4: ='Stakeholder list'!C9 | C4: ='Stakeholder list'!D9 | D4: ='Stakeholder list'!E9 | E4: ='Stakeholder list'!F9 | F4: ='Stakeholder list'!G9 | G4: ='Stakeholder list'!H9 | H4: ='Stakeholder list'!I9 | ... R4: ='Stakeholder list'!S9
A5: ='Stakeholder list'!B10 | B5: ='Stakeholder list'!C10 | C5: ='Stakeholder list'!D10 | D5: ='Stakeholder list'!E10 | E5: ='Stakeholder list'!F10 | F5: ='Stakeholder list'!G10 | G5: ='Stakeholder list'!H10 | H5: ='Stakeholder list'!I10 | ... R5: ='Stakeholder list'!S10
A6: ='Stakeholder list'!B11 | B6: ='Stakeholder list'!C11 | C6: ='Stakeholder list'!D11 | D6: ='Stakeholder list'!E11 | E6: ='Stakeholder list'!F11 | F6: ='Stakeholder list'!G11 | G6: ='Stakeholder list'!H11 | H6: ='Stakeholder list'!I11 | ... R6: ='Stakeholder list'!S11
A7: ='Stakeholder list'!B12 | B7: ='Stakeholder list'!C12 | C7: ='Stakeholder list'!D12 | D7: ='Stakeholder list'!E12 | E7: ='Stakeholder list'!F12 | F7: ='Stakeholder list'!G12 | G7: ='Stakeholder list'!H12 | H7: ='Stakeholder list'!I12 | ... R7: ='Stakeholder list'!S12
A8: ='Stakeholder list'!B13 | B8: ='Stakeholder list'!C13 | C8: ='Stakeholder list'!D13 | D8: ='Stakeholder list'!E13 | E8: ='Stakeholder list'!F13 | F8: ='Stakeholder list'!G13 | G8: ='Stakeholder list'!H13 | H8: ='Stakeholder list'!I13 | ... R8: ='Stakeholder list'!S13
A9: ='Stakeholder list'!B14 | B9: ='Stakeholder list'!C14 | C9: ='Stakeholder list'!D14 | D9: ='Stakeholder list'!E14 | E9: ='Stakeholder list'!F14 | F9: ='Stakeholder list'!G14 | G9: ='Stakeholder list'!H14 | H9: ='Stakeholder list'!I14 | ... R9: ='Stakeholder list'!S14
A10: ='Stakeholder list'!B15 | B10: ='Stakeholder list'!C15 | C10: ='Stakeholder list'!D15 | D10: ='Stakeholder list'!E15 | E10: ='Stakeholder list'!F15 | F10: ='Stakeholder list'!G15 | G10: ='Stakeholder list'!H15 | H10: ='Stakeholder list'!I15 | ... R10: ='Stakeholder list'!S15
A11: ='Stakeholder list'!B16 | B11: ='Stakeholder list'!C16 | C11: ='Stakeholder list'!D16 | D11: ='Stakeholder list'!E16 | E11: ='Stakeholder list'!F16 | F11: ='Stakeholder list'!G16 | G11: ='Stakeholder list'!H16 | H11: ='Stakeholder list'!I16 | ... R11: ='Stakeholder list'!S16
A12: ='Stakeholder list'!B17 | B12: ='Stakeholder list'!C17 | C12: ='Stakeholder list'!D17 | D12: ='Stakeholder list'!E17 | E12: ='Stakeholder list'!F17 | F12: ='Stakeholder list'!G17 | G12: ='Stakeholder list'!H17 | H12: ='Stakeholder list'!I17 | ... R12: ='Stakeholder list'!S17
... A14: ='Stakeholder list'!B19 | B14: ='Stakeholder list'!C19 | C14: ='Stakeholder list'!D19 | D14: ='Stakeholder list'!E19 | E14: ='Stakeholder list'!F19 | F14: ='Stakeholder list'!G19 | G14: ='Stakeholder list'!H19 | H14: ='Stakeholder list'!I19 | ... R14: ='Stakeholder list'!S19
A15: ='Stakeholder list'!B20 | B15: ='Stakeholder list'!C20 | C15: ='Stakeholder list'!D20 | D15: ='Stakeholder list'!E20 | E15: ='Stakeholder list'!F20 | F15: ='Stakeholder list'!G20 | G15: ='Stakeholder list'!H20 | H15: ='Stakeholder list'!I20 | ... W15: ='Stakeholder list'!X20
A16: ='Stakeholder list'!B21 | B16: ='Stakeholder list'!C21 | C16: ='Stakeholder list'!D21 | D16: ='Stakeholder list'!E21 | E16: ='Stakeholder list'!F21 | F16: ='Stakeholder list'!G21 | G16: ='Stakeholder list'!H21 | H16: ='Stakeholder list'!I21 | ... W16: ='Stakeholder list'!X21
A17: ='Stakeholder list'!B22 | B17: ='Stakeholder list'!C22 | C17: ='Stakeholder list'!D22 | D17: ='Stakeholder list'!E22 | E17: ='Stakeholder list'!F22 | F17: ='Stakeholder list'!G22 | G17: ='Stakeholder list'!H22 | H17: ='Stakeholder list'!I22 | ... W17: ='Stakeholder list'!X22
A18: ='Stakeholder list'!B23 | B18: ='Stakeholder list'!C23 | C18: ='Stakeholder list'!D23 | D18: ='Stakeholder list'!E23 | E18: ='Stakeholder list'!F23 | F18: ='Stakeholder list'!G23 | G18: ='Stakeholder list'!H23 | H18: ='Stakeholder list'!I23 | ... W18: ='Stakeholder list'!X23
A19: ='Stakeholder list'!B24 | B19: ='Stakeholder list'!C24 | C19: ='Stakeholder list'!D24 | D19: ='Stakeholder list'!E24 | E19: ='Stakeholder list'!F24 | F19: ='Stakeholder list'!G24 | G19: ='Stakeholder list'!H24 | H19: ='Stakeholder list'!I24 | ... W19: ='Stakeholder list'!X24
A20: ='Stakeholder list'!B25 | B20: ='Stakeholder list'!C25 | C20: ='Stakeholder list'!D25 | D20: ='Stakeholder list'!E25 | E20: ='Stakeholder list'!F25 | F20: ='Stakeholder list'!G25 | G20: ='Stakeholder list'!H25 | H20: ='Stakeholder list'!I25 | ... W20: ='Stakeholder list'!X25
A21: ='Stakeholder list'!B26 | B21: ='Stakeholder list'!C26 | C21: ='Stakeholder list'!D26 | D21: ='Stakeholder list'!E26 | E21: ='Stakeholder list'!F26 | F21: ='Stakeholder list'!G26 | G21: ='Stakeholder list'!H26 | H21: ='Stakeholder list'!I26 | ... W21: ='Stakeholder list'!X26
A22: ='Stakeholder list'!B27 | B22: ='Stakeholder list'!C27 | C22: ='Stakeholder list'!D27 | D22: ='Stakeholder list'!E27 | E22: ='Stakeholder list'!F27 | F22: ='Stakeholder list'!G27 | G22: ='Stakeholder list'!H27 | H22: ='Stakeholder list'!I27 | ... W22: ='Stakeholder list'!X27
A23: ='Stakeholder list'!B28 | B23: ='Stakeholder list'!C28 | C23: ='Stakeholder list'!D28 | D23: ='Stakeholder list'!E28 | E23: ='Stakeholder list'!F28 | F23: ='Stakeholder list'!G28 | G23: ='Stakeholder list'!H28 | H23: ='Stakeholder list'!I28 | ... W23: ='Stakeholder list'!X28
A24: ='Stakeholder list'!B29 | B24: ='Stakeholder list'!C29 | C24: ='Stakeholder list'!D29 | D24: ='Stakeholder list'!E29 | E24: ='Stakeholder list'!F29 | F24: ='Stakeholder list'!G29 | G24: ='Stakeholder list'!H29 | H24: ='Stakeholder list'!I29 | ... W24: ='Stakeholder list'!X29
A25: ='Stakeholder list'!B30 | B25: ='Stakeholder list'!C30 | C25: ='Stakeholder list'!D30 | D25: ='Stakeholder list'!E30 | E25: ='Stakeholder list'!F30 | F25: ='Stakeholder list'!G30 | G25: ='Stakeholder list'!H30 | H25: ='Stakeholder list'!I30 | ... W25: ='Stakeholder list'!X30
A26: ='Stakeholder list'!B31 | B26: ='Stakeholder list'!C31 | C26: ='Stakeholder list'!D31 | D26: ='Stakeholder list'!E31 | E26: ='Stakeholder list'!F31 | F26: ='Stakeholder list'!G31 | G26: ='Stakeholder list'!H31 | H26: ='Stakeholder list'!I31 | ... W26: ='Stakeholder list'!X31
... A361: ='Stakeholder list'!B366 | B361: ='Stakeholder list'!C366 | C361: ='Stakeholder list'!D366 | D361: ='Stakeholder list'!E366 | E361: ='Stakeholder list'!F366 | F361: ='Stakeholder list'!G366 | G361: ='Stakeholder list'!H366 | H361: ='Stakeholder list'!I366 | ... W361: ='Stakeholder list'!X366
A362: ='Stakeholder list'!B368 | B362: ='Stakeholder list'!C368 | C362: ='Stakeholder list'!D368 | D362: ='Stakeholder list'!E368 | E362: ='Stakeholder list'!F368 | F362: ='Stakeholder list'!G368 | G362: ='Stakeholder list'!H368 | H362: ='Stakeholder list'!I368 | ... R362: ='Stakeholder list'!S368
A363: ='Stakeholder list'!B369 | B363: ='Stakeholder list'!C369 | C363: ='Stakeholder list'!D369 | D363: ='Stakeholder list'!E369 | E363: ='Stakeholder list'!F369 | F363: ='Stakeholder list'!G369 | G363: ='Stakeholder list'!H369 | H363: ='Stakeholder list'!I369 | ... R363: ='Stakeholder list'!S369
A364: ='Stakeholder list'!B370 | B364: ='Stakeholder list'!C370 | C364: ='Stakeholder list'!D370 | D364: ='Stakeholder list'!E370 | E364: ='Stakeholder list'!F370 | F364: ='Stakeholder list'!G370 | G364: ='Stakeholder list'!H370 | H364: ='Stakeholder list'!I370 | ... R364: ='Stakeholder list'!S370
A365: ='Stakeholder list'!B371 | B365: ='Stakeholder list'!C371 | C365: ='Stakeholder list'!D371 | D365: ='Stakeholder list'!E371 | E365: ='Stakeholder list'!F371 | F365: ='Stakeholder list'!G371 | G365: ='Stakeholder list'!H371 | H365: ='Stakeholder list'!I371 | ... R365: ='Stakeholder list'!S371
A366: ='Stakeholder list'!B372 | B366: ='Stakeholder list'!C372 | C366: ='Stakeholder list'!D372 | D366: ='Stakeholder list'!E372 | E366: ='Stakeholder list'!F372 | F366: ='Stakeholder list'!G372 | G366: ='Stakeholder list'!H372 | H366: ='Stakeholder list'!I372 | ... R366: ='Stakeholder list'!S372
A367: ='Stakeholder list'!B373 | B367: ='Stakeholder list'!C373 | C367: ='Stakeholder list'!D373 | D367: ='Stakeholder list'!E373 | E367: ='Stakeholder list'!F373 | F367: ='Stakeholder list'!G373 | G367: ='Stakeholder list'!H373 | H367: ='Stakeholder list'!I373 | ... R367: ='Stakeholder list'!S373
A368: ='Stakeholder list'!B374 | B368: ='Stakeholder list'!C374 | C368: ='Stakeholder list'!D374 | D368: ='Stakeholder list'!E374 | E368: ='Stakeholder list'!F374 | F368: ='Stakeholder list'!G374 | G368: ='Stakeholder list'!H374
A369: ='Stakeholder list'!B375 | B369: ='Stakeholder list'!C375 | C369: ='Stakeholder list'!D375 | D369: ='Stakeholder list'!E375 | E369: ='Stakeholder list'!F375 | F369: ='Stakeholder list'!G375 | G369: ='Stakeholder list'!H375

Sheet Página11
A1: Stakeholder | B1: Type of organization
A2: Instituto Alana | B2: Think tanks
A3: Instituto Socioambiental (ISA) | B3: Local implementers
A4: The Nature Conservancy Brasil (TNC Brasil) | B4: Local implementers
A5: Conservação Internacional Brasil (CI-Brasil) | B5: Local implementers
A6: WWF-Brasil | B6: Local implementers
A7: Fundação SOS Mata Atlântica | B7: Local implementers
A8: Fundação Amazonas Sustentável (FAS) | B8: Local implementers
A9: Instituto de Manejo e Certificação Florestal e Agrícola (Imaflora) | B9: Local implementers
A10: Instituto de Conservação e Desenvolvimento Sustentável da Amazônia (IDESAM) | B10: Local implementers
A11: Artemisia | B11: Local implementers
A12: Instituto Conexões Sustentáveis (Conexsus) | B12: Local implementers
... A42: Visão Mundial (Visão Mundial) | B42: Local implementers

Sheet Bridge_Primary_Impact_Area
A1: =IFERROR(__xludf.DUMMYFUNCTION("ARRAYFORMULA(QUERY(SUBSTITUTE(SPLIT(FLATTEN(Data_Looker!B1:B339 & ""|"" & SPLIT(SUBSTITUTE(Data_Looker!G1:G339, ""Land, Food and Forest"", ""PROTEGER1""), "", "", FALSE)), ""|""), ""PROTEGER1"", ""Land, Food and Forest""), ""where Col2 <> ''""))"),"Stakeholder ") | B1: =IFERROR(__xludf.DUMMYFUNCTION("""COMPUTED_VALUE"""),"Primary impact area (sector of interest / Nexuses)")
A2: =IFERROR(__xludf.DUMMYFUNCTION("""COMPUTED_VALUE"""),"Instituto Ibirapitanga") | B2: =IFERROR(__xludf.DUMMYFUNCTION("""COMPUTED_VALUE"""),"""Land, Food and Forest""")
A3: =IFERROR(__xludf.DUMMYFUNCTION("""COMPUTED_VALUE"""),"Instituto Serrapilheira") | B3: =IFERROR(__xludf.DUMMYFUNCTION("""COMPUTED_VALUE"""),"""Land, Food and Forest""")
A4: =IFERROR(__xludf.DUMMYFUNCTION("""COMPUTED_VALUE"""),"Fundo Brasileiro para a Biodiversidade (FUNBIO)") | B4: =IFERROR(__xludf.DUMMYFUNCTION("""COMPUTED_VALUE"""),"""Land, Food and Forest""")
A5: =IFERROR(__xludf.DUMMYFUNCTION("""COMPUTED_VALUE"""),"Instituto Clima e Sociedade (iCS)") | B5: =IFERROR(__xludf.DUMMYFUNCTION("""COMPUTED_VALUE"""),"Buildings & Transport")
A6: =IFERROR(__xludf.DUMMYFUNCTION("""COMPUTED_VALUE"""),"Instituto Clima e Sociedade (iCS)") | B6: =IFERROR(__xludf.DUMMYFUNCTION("""COMPUTED_VALUE"""),"Energy")
A7: =IFERROR(__xludf.DUMMYFUNCTION("""COMPUTED_VALUE"""),"Instituto Clima e Sociedade (iCS)") | B7: =IFERROR(__xludf.DUMMYFUNCTION("""COMPUTED_VALUE"""),"""Land, Food and Forest""")
A8: =IFERROR(__xludf.DUMMYFUNCTION("""COMPUTED_VALUE"""),"Instituto Cultura, Comunicação e Incidência (ICCI)") | B8: =IFERROR(__xludf.DUMMYFUNCTION("""COMPUTED_VALUE"""),"Buildings & Transport")
A9: =IFERROR(__xludf.DUMMYFUNCTION("""COMPUTED_VALUE"""),"Instituto Cultura, Comunicação e Incidência (ICCI)") | B9: =IFERROR(__xludf.DUMMYFUNCTION("""COMPUTED_VALUE"""),"Energy")
A10: =IFERROR(__xludf.DUMMYFUNCTION("""COMPUTED_VALUE"""),"Instituto Cultura, Comunicação e Incidência (ICCI)") | B10: =IFERROR(__xludf.DUMMYFUNCTION("""COMPUTED_VALUE"""),"""Land, Food and Forest""")
A11: =IFERROR(__xludf.DUMMYFUNCTION("""COMPUTED_VALUE"""),"Grupo de Institutos, Fundações e Empresas (GIFE)") | B11: =IFERROR(__xludf.DUMMYFUNCTION("""COMPUTED_VALUE"""),"Buildings & Transport")
A12: =IFERROR(__xludf.DUMMYFUNCTION("""COMPUTED_VALUE"""),"Grupo de Institutos, Fundações e Empresas (GIFE)") | B12: =IFERROR(__xludf.DUMMYFUNCTION("""COMPUTED_VALUE"""),"Energy")
A13: =IFERROR(__xludf.DUMMYFUNCTION("""COMPUTED_VALUE"""),"Grupo de Institutos, Fundações e Empresas (GIFE)") | B13: =IFERROR(__xludf.DUMMYFUNCTION("""COMPUTED_VALUE"""),"""Land, Food and Forest""")
A14: =IFERROR(__xludf.DUMMYFUNCTION("""COMPUTED_VALUE"""),"Movimento Bem Maior (MBM)") | B14: =IFERROR(__xludf.DUMMYFUNCTION("""COMPUTED_VALUE"""),"Buildings & Transport")
A15: =IFERROR(__xludf.DUMMYFUNCTION("""COMPUTED_VALUE"""),"Movimento Bem Maior (MBM)") | B15: =IFERROR(__xludf.DUMMYFUNCTION("""COMPUTED_VALUE"""),"""Land, Food and Forest""")
A16: =IFERROR(__xludf.DUMMYFUNCTION("""COMPUTED_VALUE"""),"Instituto Beija ") | B16: =IFERROR(__xludf.DUMMYFUNCTION("""COMPUTED_VALUE"""),"Buildings & Transport")
A17: =IFERROR(__xludf.DUMMYFUNCTION("""COMPUTED_VALUE"""),"Instituto Beija ") | B17: =IFERROR(__xludf.DUMMYFUNCTION("""COMPUTED_VALUE"""),"Energy")
A18: =IFERROR(__xludf.DUMMYFUNCTION("""COMPUTED_VALUE"""),"Instituto Beija ") | B18: =IFERROR(__xludf.DUMMYFUNCTION("""COMPUTED_VALUE"""),"""Land, Food and Forest""")
A19: =IFERROR(__xludf.DUMMYFUNCTION("""COMPUTED_VALUE"""),"Instituto Beija ") | B19: =IFERROR(__xludf.DUMMYFUNCTION("""COMPUTED_VALUE"""),"Emergency response")
A20: =IFERROR(__xludf.DUMMYFUNCTION("""COMPUTED_VALUE"""),"Open Society Foundations") | B20: =IFERROR(__xludf.DUMMYFUNCTION("""COMPUTED_VALUE"""),"Buildings & Transport")
A21: =IFERROR(__xludf.DUMMYFUNCTION("""COMPUTED_VALUE"""),"Open Society Foundations") | B21: =IFERROR(__xludf.DUMMYFUNCTION("""COMPUTED_VALUE"""),"Emergency response")
A22: =IFERROR(__xludf.DUMMYFUNCTION("""COMPUTED_VALUE"""),"Open Society Foundations") | B22: =IFERROR(__xludf.DUMMYFUNCTION("""COMPUTED_VALUE"""),"Energy")
A23: =IFERROR(__xludf.DUMMYFUNCTION("""COMPUTED_VALUE"""),"Open Society Foundations") | B23: =IFERROR(__xludf.DUMMYFUNCTION("""COMPUTED_VALUE"""),"""Land, Food and Forest""")
A24: =IFERROR(__xludf.DUMMYFUNCTION("""COMPUTED_VALUE"""),"Instituto Ethos") | B24: =IFERROR(__xludf.DUMMYFUNCTION("""COMPUTED_VALUE"""),"Buildings & Transport")
A25: =IFERROR(__xludf.DUMMYFUNCTION("""COMPUTED_VALUE"""),"Instituto Ethos") | B25: =IFERROR(__xludf.DUMMYFUNCTION("""COMPUTED_VALUE"""),"Energy")
A26: =IFERROR(__xludf.DUMMYFUNCTION("""COMPUTED_VALUE"""),"Instituto Ethos") | B26: =IFERROR(__xludf.DUMMYFUNCTION("""COMPUTED_VALUE"""),"""Land, Food and Forest""")
A27: =IFERROR(__xludf.DUMMYFUNCTION("""COMPUTED_VALUE"""),"Instituto para o Desenvolvimento do Investimento Social (IDIS)") | B27: =IFERROR(__xludf.DUMMYFUNCTION("""COMPUTED_VALUE"""),"Buildings & Transport")
A28: =IFERROR(__xludf.DUMMYFUNCTION("""COMPUTED_VALUE"""),"Instituto para o Desenvolvimento do Investimento Social (IDIS)") | B28: =IFERROR(__xludf.DUMMYFUNCTION("""COMPUTED_VALUE"""),"Energy")
A29: =IFERROR(__xludf.DUMMYFUNCTION("""COMPUTED_VALUE"""),"Instituto para o Desenvolvimento do Investimento Social (IDIS)") | B29: =IFERROR(__xludf.DUMMYFUNCTION("""COMPUTED_VALUE"""),"""Land, Food and Forest""")
A30: =IFERROR(__xludf.DUMMYFUNCTION("""COMPUTED_VALUE"""),"Instituto Climate Ventures Brasil (Climate Ventures)") | B30: =IFERROR(__xludf.DUMMYFUNCTION("""COMPUTED_VALUE"""),"Buildings & Transport")
A31: =IFERROR(__xludf.DUMMYFUNCTION("""COMPUTED_VALUE"""),"Instituto Climate Ventures Brasil (Climate Ventures)") | B31: =IFERROR(__xludf.DUMMYFUNCTION("""COMPUTED_VALUE"""),"Energy")
A32: =IFERROR(__xludf.DUMMYFUNCTION("""COMPUTED_VALUE"""),"Instituto Climate Ventures Brasil (Climate Ventures)") | B32: =IFERROR(__xludf.DUMMYFUNCTION("""COMPUTED_VALUE"""),"""Land, Food and Forest""")
A33: =IFERROR(__xludf.DUMMYFUNCTION("""COMPUTED_VALUE"""),"The Climate Group") | B33: =IFERROR(__xludf.DUMMYFUNCTION("""COMPUTED_VALUE"""),"Buildings & Transport")
A34: =IFERROR(__xludf.DUMMYFUNCTION("""COMPUTED_VALUE"""),"The Climate Group") | B34: =IFERROR(__xludf.DUMMYFUNCTION("""COMPUTED_VALUE"""),"Energy")
A35: =IFERROR(__xludf.DUMMYFUNCTION("""COMPUTED_VALUE"""),"Fundação Arymax") | B35: =IFERROR(__xludf.DUMMYFUNCTION("""COMPUTED_VALUE"""),"Emergency response")
A36: =IFERROR(__xludf.DUMMYFUNCTION("""COMPUTED_VALUE"""),"Fundação Arymax") | B36: =IFERROR(__xludf.DUMMYFUNCTION("""COMPUTED_VALUE"""),"""Land, Food and Forest""")
A37: =IFERROR(__xludf.DUMMYFUNCTION("""COMPUTED_VALUE"""),"Instituto Talanoa") | B37: =IFERROR(__xludf.DUMMYFUNCTION("""COMPUTED_VALUE"""),"Buildings & Transport")
A38: =IFERROR(__xludf.DUMMYFUNCTION("""COMPUTED_VALUE"""),"Instituto Talanoa") | B38: =IFERROR(__xludf.DUMMYFUNCTION("""COMPUTED_VALUE"""),"Energy")
A39: =IFERROR(__xludf.DUMMYFUNCTION("""COMPUTED_VALUE"""),"Instituto Talanoa") | B39: =IFERROR(__xludf.DUMMYFUNCTION("""COMPUTED_VALUE"""),"""Land, Food and Forest""")
A40: =IFERROR(__xludf.DUMMYFUNCTION("""COMPUTED_VALUE"""),"Instituto Alana") | B40: =IFERROR(__xludf.DUMMYFUNCTION("""COMPUTED_VALUE"""),"""Land, Food and Forest""")
A41: =IFERROR(__xludf.DUMMYFUNCTION("""COMPUTED_VALUE"""),"Itaúsa (Itaúsa S.A.)") | B41: =IFERROR(__xludf.DUMMYFUNCTION("""COMPUTED_VALUE"""),"Buildings & Transport")
A42: =IFERROR(__xludf.DUMMYFUNCTION("""COMPUTED_VALUE"""),"Itaúsa (Itaúsa S.A.)") | B42: =IFERROR(__xludf.DUMMYFUNCTION("""COMPUTED_VALUE"""),"Energy")
A43: =IFERROR(__xludf.DUMMYFUNCTION("""COMPUTED_VALUE"""),"Itaúsa (Itaúsa S.A.)") | B43: =IFERROR(__xludf.DUMMYFUNCTION("""COMPUTED_VALUE"""),"""Land, Food and Forest""")
A44: =IFERROR(__xludf.DUMMYFUNCTION("""COMPUTED_VALUE"""),"Instituto Arapyaú") | B44: =IFERROR(__xludf.DUMMYFUNCTION("""COMPUTED_VALUE"""),"Buildings & Transport")
A45: =IFERROR(__xludf.DUMMYFUNCTION("""COMPUTED_VALUE"""),"Instituto Arapyaú") | B45: =IFERROR(__xludf.DUMMYFUNCTION("""COMPUTED_VALUE"""),"Energy")
A46: =IFERROR(__xludf.DUMMYFUNCTION("""COMPUTED_VALUE"""),"Instituto Arapyaú") | B46: =IFERROR(__xludf.DUMMYFUNCTION("""COMPUTED_VALUE"""),"""Land, Food and Forest""")
A47: =IFERROR(__xludf.DUMMYFUNCTION("""COMPUTED_VALUE"""),"Instituto Semeia") | B47: =IFERROR(__xludf.DUMMYFUNCTION("""COMPUTED_VALUE"""),"""Land, Food and Forest""")
A48: =IFERROR(__xludf.DUMMYFUNCTION("""COMPUTED_VALUE"""),"The David and Lucile Packard Foundation") | B48: =IFERROR(__xludf.DUMMYFUNCTION("""COMPUTED_VALUE"""),"Energy")
A49: =IFERROR(__xludf.DUMMYFUNCTION("""COMPUTED_VALUE"""),"The David and Lucile Packard Foundation") | B49: =IFERROR(__xludf.DUMMYFUNCTION("""COMPUTED_VALUE"""),"""Land, Food and Forest""")
A50: =IFERROR(__xludf.DUMMYFUNCTION("""COMPUTED_VALUE"""),"Alcoa") | B50: =IFERROR(__xludf.DUMMYFUNCTION("""COMPUTED_VALUE"""),"Buildings & Transport")
A51: =IFERROR(__xludf.DUMMYFUNCTION("""COMPUTED_VALUE"""),"Alcoa") | B51: =IFERROR(__xludf.DUMMYFUNCTION("""COMPUTED_VALUE"""),"Energy")
A52: =IFERROR(__xludf.DUMMYFUNCTION("""COMPUTED_VALUE"""),"Norsk Hydro ASA (Hydro)") | B52: =IFERROR(__xludf.DUMMYFUNCTION("""COMPUTED_VALUE"""),"Buildings & Transport")
A53: =IFERROR(__xludf.DUMMYFUNCTION("""COMPUTED_VALUE"""),"Norsk Hydro ASA (Hydro)") | B53: =IFERROR(__xludf.DUMMYFUNCTION("""COMPUTED_VALUE"""),"Energy")
A54: =IFERROR(__xludf.DUMMYFUNCTION("""COMPUTED_VALUE"""),"Instituto Socioambiental (ISA)") | B54: =IFERROR(__xludf.DUMMYFUNCTION("""COMPUTED_VALUE"""),"""Land, Food and Forest""")
A55: =IFERROR(__xludf.DUMMYFUNCTION("""COMPUTED_VALUE"""),"The Nature Conservancy Brasil (TNC Brasil)") | B55: =IFERROR(__xludf.DUMMYFUNCTION("""COMPUTED_VALUE"""),"""Land, Food and Forest""")
A56: =IFERROR(__xludf.DUMMYFUNCTION("""COMPUTED_VALUE"""),"Conservação Internacional Brasil (CI-Brasil)") | B56: =IFERROR(__xludf.DUMMYFUNCTION("""COMPUTED_VALUE"""),"""Land, Food and Forest""")
A57: =IFERROR(__xludf.DUMMYFUNCTION("""COMPUTED_VALUE"""),"WWF-Brasil") | B57: =IFERROR(__xludf.DUMMYFUNCTION("""COMPUTED_VALUE"""),"""Land, Food and Forest""")
A58: =IFERROR(__xludf.DUMMYFUNCTION("""COMPUTED_VALUE"""),"WRI Brasil") | B58: =IFERROR(__xludf.DUMMYFUNCTION("""COMPUTED_VALUE"""),"Buildings & Transport")
A59: =IFERROR(__xludf.DUMMYFUNCTION("""COMPUTED_VALUE"""),"WRI Brasil") | B59: =IFERROR(__xludf.DUMMYFUNCTION("""COMPUTED_VALUE"""),"Energy")
A60: =IFERROR(__xludf.DUMMYFUNCTION("""COMPUTED_VALUE"""),"WRI Brasil") | B60: =IFERROR(__xludf.DUMMYFUNCTION("""COMPUTED_VALUE"""),"""Land, Food and Forest""")
A61: =IFERROR(__xludf.DUMMYFUNCTION("""COMPUTED_VALUE"""),"Fundação SOS Mata Atlântica") | B61: =IFERROR(__xludf.DUMMYFUNCTION("""COMPUTED_VALUE"""),"""Land, Food and Forest""")
A62: =IFERROR(__xludf.DUMMYFUNCTION("""COMPUTED_VALUE"""),"Empresa Brasileira de Pesquisa Agropecuária (Embrapa)") | B62: =IFERROR(__xludf.DUMMYFUNCTION("""COMPUTED_VALUE"""),"""Land, Food and Forest""")
A63: =IFERROR(__xludf.DUMMYFUNCTION("""COMPUTED_VALUE"""),"Sistema S") | B63: =IFERROR(__xludf.DUMMYFUNCTION("""COMPUTED_VALUE"""),"Buildings & Transport")
A64: =IFERROR(__xludf.DUMMYFUNCTION("""COMPUTED_VALUE"""),"Sistema S") | B64: =IFERROR(__xludf.DUMMYFUNCTION("""COMPUTED_VALUE"""),"Energy")
A65: =IFERROR(__xludf.DUMMYFUNCTION("""COMPUTED_VALUE"""),"Instituto Brasileiro do Meio Ambiente e dos Recursos Naturais Renováveis (Ibama)") | B65: =IFERROR(__xludf.DUMMYFUNCTION("""COMPUTED_VALUE"""),"Energy")
A66: =IFERROR(__xludf.DUMMYFUNCTION("""COMPUTED_VALUE"""),"Instituto Brasileiro do Meio Ambiente e dos Recursos Naturais Renováveis (Ibama)") | B66: =IFERROR(__xludf.DUMMYFUNCTION("""COMPUTED_VALUE"""),"""Land, Food and Forest""")
A67: =IFERROR(__xludf.DUMMYFUNCTION("""COMPUTED_VALUE"""),"Instituto Chico Mendes de Conservação da Biodiversidade (ICMBio)") | B67: =IFERROR(__xludf.DUMMYFUNCTION("""COMPUTED_VALUE"""),"""Land, Food and Forest""")
A68: =IFERROR(__xludf.DUMMYFUNCTION("""COMPUTED_VALUE"""),"Instituto do Homem e Meio Ambiente da Amazônia (Imazon)") | B68: =IFERROR(__xludf.DUMMYFUNCTION("""COMPUTED_VALUE"""),"""Land, Food and Forest""")
A69: =IFERROR(__xludf.DUMMYFUNCTION("""COMPUTED_VALUE"""),"Fundação Amazonas Sustentável (FAS)") | B69: =IFERROR(__xludf.DUMMYFUNCTION("""COMPUTED_VALUE"""),"""Land, Food and Forest""")
A70: =IFERROR(__xludf.DUMMYFUNCTION("""COMPUTED_VALUE"""),"Instituto de Manejo e Certificação Florestal e Agrícola (Imaflora)") | B70: =IFERROR(__xludf.DUMMYFUNCTION("""COMPUTED_VALUE"""),"""Land, Food and Forest""")
A71: =IFERROR(__xludf.DUMMYFUNCTION("""COMPUTED_VALUE"""),"Fundação Roberto Marinho") | B71: =IFERROR(__xludf.DUMMYFUNCTION("""COMPUTED_VALUE"""),"Buildings & Transport")
A72: =IFERROR(__xludf.DUMMYFUNCTION("""COMPUTED_VALUE"""),"Fundação Roberto Marinho") | B72: =IFERROR(__xludf.DUMMYFUNCTION("""COMPUTED_VALUE"""),"""Land, Food and Forest""")
A73: =IFERROR(__xludf.DUMMYFUNCTION("""COMPUTED_VALUE"""),"Instituto Serzedello Corrêa (ISC/TCU)") | B73: =IFERROR(__xludf.DUMMYFUNCTION("""COMPUTED_VALUE"""),"Buildings & Transport")
A74: =IFERROR(__xludf.DUMMYFUNCTION("""COMPUTED_VALUE"""),"Instituto Serzedello Corrêa (ISC/TCU)") | B74: =IFERROR(__xludf.DUMMYFUNCTION("""COMPUTED_VALUE"""),"Energy")
A75: =IFERROR(__xludf.DUMMYFUNCTION("""COMPUTED_VALUE"""),"Instituto Serzedello Corrêa (ISC/TCU)") | B75: =IFERROR(__xludf.DUMMYFUNCTION("""COMPUTED_VALUE"""),"""Land, Food and Forest""")
A76: =IFERROR(__xludf.DUMMYFUNCTION("""COMPUTED_VALUE"""),"Vale S.A.") | B76: =IFERROR(__xludf.DUMMYFUNCTION("""COMPUTED_VALUE"""),"Buildings & Transport")
A77: =IFERROR(__xludf.DUMMYFUNCTION("""COMPUTED_VALUE"""),"Vale S.A.") | B77: =IFERROR(__xludf.DUMMYFUNCTION("""COMPUTED_VALUE"""),"Energy")
A78: =IFERROR(__xludf.DUMMYFUNCTION("""COMPUTED_VALUE"""),"Vale S.A.") | B78: =IFERROR(__xludf.DUMMYFUNCTION("""COMPUTED_VALUE"""),"""Land, Food and Forest""")
A79: =IFERROR(__xludf.DUMMYFUNCTION("""COMPUTED_VALUE"""),"Suzano S.A.") | B79: =IFERROR(__xludf.DUMMYFUNCTION("""COMPUTED_VALUE"""),"Energy")
A80: =IFERROR(__xludf.DUMMYFUNCTION("""COMPUTED_VALUE"""),"Suzano S.A.") | B80: =IFERROR(__xludf.DUMMYFUNCTION("""COMPUTED_VALUE"""),"""Land, Food and Forest""")
A81: =IFERROR(__xludf.DUMMYFUNCTION("""COMPUTED_VALUE"""),"Banco da Amazônia S.A. (BASA)") | B81: =IFERROR(__xludf.DUMMYFUNCTION("""COMPUTED_VALUE"""),"Energy")
A82: =IFERROR(__xludf.DUMMYFUNCTION("""COMPUTED_VALUE"""),"Banco da Amazônia S.A. (BASA)") | B82: =IFERROR(__xludf.DUMMYFUNCTION("""COMPUTED_VALUE"""),"""Land, Food and Forest""")
A83: =IFERROR(__xludf.DUMMYFUNCTION("""COMPUTED_VALUE"""),"Instituto de Conservação e Desenvolvimento Sustentável da Amazônia (IDESAM)") | B83: =IFERROR(__xludf.DUMMYFUNCTION("""COMPUTED_VALUE"""),"""Land, Food and Forest""")
A84: =IFERROR(__xludf.DUMMYFUNCTION("""COMPUTED_VALUE"""),"Sitawi Finanças do Bem") | B84: =IFERROR(__xludf.DUMMYFUNCTION("""COMPUTED_VALUE"""),"Buildings & Transport")
A85: =IFERROR(__xludf.DUMMYFUNCTION("""COMPUTED_VALUE"""),"Sitawi Finanças do Bem") | B85: =IFERROR(__xludf.DUMMYFUNCTION("""COMPUTED_VALUE"""),"Energy")
A86: =IFERROR(__xludf.DUMMYFUNCTION("""COMPUTED_VALUE"""),"Sitawi Finanças do Bem") | B86: =IFERROR(__xludf.DUMMYFUNCTION("""COMPUTED_VALUE"""),"""Land, Food and Forest""")
A87: =IFERROR(__xludf.DUMMYFUNCTION("""COMPUTED_VALUE"""),"Din4mo") | B87: =IFERROR(__xludf.DUMMYFUNCTION("""COMPUTED_VALUE"""),"Buildings & Transport")
A88: =IFERROR(__xludf.DUMMYFUNCTION("""COMPUTED_VALUE"""),"Din4mo") | B88: =IFERROR(__xludf.DUMMYFUNCTION("""COMPUTED_VALUE"""),"Energy")
A89: =IFERROR(__xludf.DUMMYFUNCTION("""COMPUTED_VALUE"""),"Din4mo") | B89: =IFERROR(__xludf.DUMMYFUNCTION("""COMPUTED_VALUE"""),"""Land, Food and Forest""")
A90: =IFERROR(__xludf.DUMMYFUNCTION("""COMPUTED_VALUE"""),"Artemisia") | B90: =IFERROR(__xludf.DUMMYFUNCTION("""COMPUTED_VALUE"""),"Buildings & Transport")
A91: =IFERROR(__xludf.DUMMYFUNCTION("""COMPUTED_VALUE"""),"Impact Hub Network") | B91: =IFERROR(__xludf.DUMMYFUNCTION("""COMPUTED_VALUE"""),"Buildings & Transport")
A92: =IFERROR(__xludf.DUMMYFUNCTION("""COMPUTED_VALUE"""),"Impact Hub Network") | B92: =IFERROR(__xludf.DUMMYFUNCTION("""COMPUTED_VALUE"""),"Energy")
A93: =IFERROR(__xludf.DUMMYFUNCTION("""COMPUTED_VALUE"""),"Impact Hub Network") | B93: =IFERROR(__xludf.DUMMYFUNCTION("""COMPUTED_VALUE"""),"""Land, Food and Forest""")
A94: =IFERROR(__xludf.DUMMYFUNCTION("""COMPUTED_VALUE"""),"Instituto Conexões Sustentáveis (Conexsus)") | B94: =IFERROR(__xludf.DUMMYFUNCTION("""COMPUTED_VALUE"""),"""Land, Food and Forest""")
A95: =IFERROR(__xludf.DUMMYFUNCTION("""COMPUTED_VALUE"""),"Pipe.Social") | B95: =IFERROR(__xludf.DUMMYFUNCTION("""COMPUTED_VALUE"""),"Buildings & Transport")
A96: =IFERROR(__xludf.DUMMYFUNCTION("""COMPUTED_VALUE"""),"Pipe.Social") | B96: =IFERROR(__xludf.DUMMYFUNCTION("""COMPUTED_VALUE"""),"Energy")
A97: =IFERROR(__xludf.DUMMYFUNCTION("""COMPUTED_VALUE"""),"Pipe.Social") | B97: =IFERROR(__xludf.DUMMYFUNCTION("""COMPUTED_VALUE"""),"""Land, Food and Forest""")
A98: =IFERROR(__xludf.DUMMYFUNCTION("""COMPUTED_VALUE"""),"Yunus Negócios Sociais (Brasil)") | B98: =IFERROR(__xludf.DUMMYFUNCTION("""COMPUTED_VALUE"""),"Buildings & Transport")
A99: =IFERROR(__xludf.DUMMYFUNCTION("""COMPUTED_VALUE"""),"Yunus Negócios Sociais (Brasil)") | B99: =IFERROR(__xludf.DUMMYFUNCTION("""COMPUTED_VALUE"""),"Energy")
A100: =IFERROR(__xludf.DUMMYFUNCTION("""COMPUTED_VALUE"""),"Yunus Negócios Sociais (Brasil)") | B100: =IFERROR(__xludf.DUMMYFUNCTION("""COMPUTED_VALUE"""),"""Land, Food and Forest""")
...

Sheet Data_aluvial_Donnors
A1: Funding Role | B1: Primary impact area (sector of interest / Nexuses)
A2: Donor | B2: Land, Food and Forest
A3: Donor | B3: Land, Food and Forest
A4: Re-granter | B4: Land, Food and Forest
A5: Re-granter | B5: Buildings & Transport
A6: Re-granter | B6: Energy
A7: Re-granter | B7: Land, Food and Forest
A8: Re-granter | B8: Buildings & Transport
A9: Re-granter | B9: Energy
A10: Re-granter | B10: Land, Food and Forest
A11: Grantee | B11: Buildings & Transport
A12: Grantee | B12: Energy
... A550: Grantee | B550: Energy

Sheet Bridge_Primary_Biome
A1: Stakeholder | B1: Biome
A2: =IFERROR(__xludf.DUMMYFUNCTION("ARRAYFORMULA(QUERY(SPLIT(FLATTEN(Data_Looker!B2:B340 & ""|"" & SPLIT(Data_Looker!H2:H340, "", "")), ""|""), ""where Col2 <> ''""))"),"Instituto Ibirapitanga") | B2: =IFERROR(__xludf.DUMMYFUNCTION("""COMPUTED_VALUE"""),"Amazonia")
A3: =IFERROR(__xludf.DUMMYFUNCTION("""COMPUTED_VALUE"""),"Fundo Brasileiro para a Biodiversidade (FUNBIO)") | B3: =IFERROR(__xludf.DUMMYFUNCTION("""COMPUTED_VALUE"""),"Amazonia")
A4: =IFERROR(__xludf.DUMMYFUNCTION("""COMPUTED_VALUE"""),"Fundo Brasileiro para a Biodiversidade (FUNBIO)") | B4: =IFERROR(__xludf.DUMMYFUNCTION("""COMPUTED_VALUE"""),"Caatinga")
A5: =IFERROR(__xludf.DUMMYFUNCTION("""COMPUTED_VALUE"""),"Fundo Brasileiro para a Biodiversidade (FUNBIO)") | B5: =IFERROR(__xludf.DUMMYFUNCTION("""COMPUTED_VALUE"""),"Cerrado")
A6: =IFERROR(__xludf.DUMMYFUNCTION("""COMPUTED_VALUE"""),"Instituto Clima e Sociedade (iCS)") | B6: =IFERROR(__xludf.DUMMYFUNCTION("""COMPUTED_VALUE"""),"Amazonia")
A7: =IFERROR(__xludf.DUMMYFUNCTION("""COMPUTED_VALUE"""),"Instituto Clima e Sociedade (iCS)") | B7: =IFERROR(__xludf.DUMMYFUNCTION("""COMPUTED_VALUE"""),"Caatinga")
A8: =IFERROR(__xludf.DUMMYFUNCTION("""COMPUTED_VALUE"""),"Instituto Clima e Sociedade (iCS)") | B8: =IFERROR(__xludf.DUMMYFUNCTION("""COMPUTED_VALUE"""),"Cerrado")
A9: =IFERROR(__xludf.DUMMYFUNCTION("""COMPUTED_VALUE"""),"Movimento Bem Maior (MBM)") | B9: =IFERROR(__xludf.DUMMYFUNCTION("""COMPUTED_VALUE"""),"Amazonia")
A10: =IFERROR(__xludf.DUMMYFUNCTION("""COMPUTED_VALUE"""),"Open Society Foundations") | B10: =IFERROR(__xludf.DUMMYFUNCTION("""COMPUTED_VALUE"""),"Amazonia")
A11: =IFERROR(__xludf.DUMMYFUNCTION("""COMPUTED_VALUE"""),"Instituto Ethos") | B11: =IFERROR(__xludf.DUMMYFUNCTION("""COMPUTED_VALUE"""),"Amazonia")
A12: =IFERROR(__xludf.DUMMYFUNCTION("""COMPUTED_VALUE"""),"Instituto Climate Ventures Brasil (Climate Ventures)") | B12: =IFERROR(__xludf.DUMMYFUNCTION("""COMPUTED_VALUE"""),"Amazonia")
A13: =IFERROR(__xludf.DUMMYFUNCTION("""COMPUTED_VALUE"""),"Instituto Climate Ventures Brasil (Climate Ventures)") | B13: =IFERROR(__xludf.DUMMYFUNCTION("""COMPUTED_VALUE"""),"Caatinga")
A14: =IFERROR(__xludf.DUMMYFUNCTION("""COMPUTED_VALUE"""),"Instituto Climate Ventures Brasil (Climate Ventures)") | B14: =IFERROR(__xludf.DUMMYFUNCTION("""COMPUTED_VALUE"""),"Cerrado")
A15: =IFERROR(__xludf.DUMMYFUNCTION("""COMPUTED_VALUE"""),"Instituto Talanoa") | B15: =IFERROR(__xludf.DUMMYFUNCTION("""COMPUTED_VALUE"""),"Amazonia")
A16: =IFERROR(__xludf.DUMMYFUNCTION("""COMPUTED_VALUE"""),"Instituto Talanoa") | B16: =IFERROR(__xludf.DUMMYFUNCTION("""COMPUTED_VALUE"""),"Caatinga")
A17: =IFERROR(__xludf.DUMMYFUNCTION("""COMPUTED_VALUE"""),"Instituto Talanoa") | B17: =IFERROR(__xludf.DUMMYFUNCTION("""COMPUTED_VALUE"""),"Cerrado")
A18: =IFERROR(__xludf.DUMMYFUNCTION("""COMPUTED_VALUE"""),"Instituto Alana") | B18: =IFERROR(__xludf.DUMMYFUNCTION("""COMPUTED_VALUE"""),"Amazonia")
A19: =IFERROR(__xludf.DUMMYFUNCTION("""COMPUTED_VALUE"""),"Instituto Alana") | B19: =IFERROR(__xludf.DUMMYFUNCTION("""COMPUTED_VALUE"""),"Caatinga")
A20: =IFERROR(__xludf.DUMMYFUNCTION("""COMPUTED_VALUE"""),"Instituto Alana") | B20: =IFERROR(__xludf.DUMMYFUNCTION("""COMPUTED_VALUE"""),"Cerrado")
A21: =IFERROR(__xludf.DUMMYFUNCTION("""COMPUTED_VALUE"""),"Instituto Arapyaú") | B21: =IFERROR(__xludf.DUMMYFUNCTION("""COMPUTED_VALUE"""),"Amazonia")
A22: =IFERROR(__xludf.DUMMYFUNCTION("""COMPUTED_VALUE"""),"Instituto Semeia") | B22: =IFERROR(__xludf.DUMMYFUNCTION("""COMPUTED_VALUE"""),"Amazonia")
A23: =IFERROR(__xludf.DUMMYFUNCTION("""COMPUTED_VALUE"""),"Instituto Semeia") | B23: =IFERROR(__xludf.DUMMYFUNCTION("""COMPUTED_VALUE"""),"Cerrado")
A24: =IFERROR(__xludf.DUMMYFUNCTION("""COMPUTED_VALUE"""),"Alcoa") | B24: =IFERROR(__xludf.DUMMYFUNCTION("""COMPUTED_VALUE"""),"Amazonia")
A25: =IFERROR(__xludf.DUMMYFUNCTION("""COMPUTED_VALUE"""),"Norsk Hydro ASA (Hydro)") | B25: =IFERROR(__xludf.DUMMYFUNCTION("""COMPUTED_VALUE"""),"Amazonia")
A26: =IFERROR(__xludf.DUMMYFUNCTION("""COMPUTED_VALUE"""),"Instituto Socioambiental (ISA)") | B26: =IFERROR(__xludf.DUMMYFUNCTION("""COMPUTED_VALUE"""),"Amazonia")
A27: =IFERROR(__xludf.DUMMYFUNCTION("""COMPUTED_VALUE"""),"The Nature Conservancy Brasil (TNC Brasil)") | B27: =IFERROR(__xludf.DUMMYFUNCTION("""COMPUTED_VALUE"""),"Amazonia")
A28: =IFERROR(__xludf.DUMMYFUNCTION("""COMPUTED_VALUE"""),"The Nature Conservancy Brasil (TNC Brasil)") | B28: =IFERROR(__xludf.DUMMYFUNCTION("""COMPUTED_VALUE"""),"Cerrado")
A29: =IFERROR(__xludf.DUMMYFUNCTION("""COMPUTED_VALUE"""),"Conservação Internacional Brasil (CI-Brasil)") | B29: =IFERROR(__xludf.DUMMYFUNCTION("""COMPUTED_VALUE"""),"Amazonia")
A30: =IFERROR(__xludf.DUMMYFUNCTION("""COMPUTED_VALUE"""),"Conservação Internacional Brasil (CI-Brasil)") | B30: =IFERROR(__xludf.DUMMYFUNCTION("""COMPUTED_VALUE"""),"Cerrado")
A31: =IFERROR(__xludf.DUMMYFUNCTION("""COMPUTED_VALUE"""),"WWF-Brasil") | B31: =IFERROR(__xludf.DUMMYFUNCTION("""COMPUTED_VALUE"""),"Amazonia")
A32: =IFERROR(__xludf.DUMMYFUNCTION("""COMPUTED_VALUE"""),"WWF-Brasil") | B32: =IFERROR(__xludf.DUMMYFUNCTION("""COMPUTED_VALUE"""),"Cerrado")
A33: =IFERROR(__xludf.DUMMYFUNCTION("""COMPUTED_VALUE"""),"WRI Brasil") | B33: =IFERROR(__xludf.DUMMYFUNCTION("""COMPUTED_VALUE"""),"Amazonia")
A34: =IFERROR(__xludf.DUMMYFUNCTION("""COMPUTED_VALUE"""),"WRI Brasil") | B34: =IFERROR(__xludf.DUMMYFUNCTION("""COMPUTED_VALUE"""),"Caatinga")
A35: =IFERROR(__xludf.DUMMYFUNCTION("""COMPUTED_VALUE"""),"WRI Brasil") | B35: =IFERROR(__xludf.DUMMYFUNCTION("""COMPUTED_VALUE"""),"Cerrado")
A36: =IFERROR(__xludf.DUMMYFUNCTION("""COMPUTED_VALUE"""),"Empresa Brasileira de Pesquisa Agropecuária (Embrapa)") | B36: =IFERROR(__xludf.DUMMYFUNCTION("""COMPUTED_VALUE"""),"Amazonia")
A37: =IFERROR(__xludf.DUMMYFUNCTION("""COMPUTED_VALUE"""),"Empresa Brasileira de Pesquisa Agropecuária (Embrapa)") | B37: =IFERROR(__xludf.DUMMYFUNCTION("""COMPUTED_VALUE"""),"Caatinga")
A38: =IFERROR(__xludf.DUMMYFUNCTION("""COMPUTED_VALUE"""),"Empresa Brasileira de Pesquisa Agropecuária (Embrapa)") | B38: =IFERROR(__xludf.DUMMYFUNCTION("""COMPUTED_VALUE"""),"Cerrado")
A39: =IFERROR(__xludf.DUMMYFUNCTION("""COMPUTED_VALUE"""),"Instituto Brasileiro do Meio Ambiente e dos Recursos Naturais Renováveis (Ibama)") | B39: =IFERROR(__xludf.DUMMYFUNCTION("""COMPUTED_VALUE"""),"Amazonia")
A40: =IFERROR(__xludf.DUMMYFUNCTION("""COMPUTED_VALUE"""),"Instituto Brasileiro do Meio Ambiente e dos Recursos Naturais Renováveis (Ibama)") | B40: =IFERROR(__xludf.DUMMYFUNCTION("""COMPUTED_VALUE"""),"Caatinga")
A41: =IFERROR(__xludf.DUMMYFUNCTION("""COMPUTED_VALUE"""),"Instituto Brasileiro do Meio Ambiente e dos Recursos Naturais Renováveis (Ibama)") | B41: =IFERROR(__xludf.DUMMYFUNCTION("""COMPUTED_VALUE"""),"Cerrado")
A42: =IFERROR(__xludf.DUMMYFUNCTION("""COMPUTED_VALUE"""),"Instituto Chico Mendes de Conservação da Biodiversidade (ICMBio)") | B42: =IFERROR(__xludf.DUMMYFUNCTION("""COMPUTED_VALUE"""),"Amazonia")
A43: =IFERROR(__xludf.DUMMYFUNCTION("""COMPUTED_VALUE"""),"Instituto Chico Mendes de Conservação da Biodiversidade (ICMBio)") | B43: =IFERROR(__xludf.DUMMYFUNCTION("""COMPUTED_VALUE"""),"Caatinga")
A44: =IFERROR(__xludf.DUMMYFUNCTION("""COMPUTED_VALUE"""),"Instituto Chico Mendes de Conservação da Biodiversidade (ICMBio)") | B44: =IFERROR(__xludf.DUMMYFUNCTION("""COMPUTED_VALUE"""),"Cerrado")
A45: =IFERROR(__xludf.DUMMYFUNCTION("""COMPUTED_VALUE"""),"Instituto do Homem e Meio Ambiente da Amazônia (Imazon)") | B45: =IFERROR(__xludf.DUMMYFUNCTION("""COMPUTED_VALUE"""),"Amazonia")
A46: =IFERROR(__xludf.DUMMYFUNCTION("""COMPUTED_VALUE"""),"Fundação Amazonas Sustentável (FAS)") | B46: =IFERROR(__xludf.DUMMYFUNCTION("""COMPUTED_VALUE"""),"Amazonia")
A47: =IFERROR(__xludf.DUMMYFUNCTION("""COMPUTED_VALUE"""),"Instituto de Manejo e Certificação Florestal e Agrícola (Imaflora)") | B47: =IFERROR(__xludf.DUMMYFUNCTION("""COMPUTED_VALUE"""),"Amazonia")
A48: =IFERROR(__xludf.DUMMYFUNCTION("""COMPUTED_VALUE"""),"Instituto de Manejo e Certificação Florestal e Agrícola (Imaflora)") | B48: =IFERROR(__xludf.DUMMYFUNCTION("""COMPUTED_VALUE"""),"Caatinga")
A49: =IFERROR(__xludf.DUMMYFUNCTION("""COMPUTED_VALUE"""),"Instituto de Manejo e Certificação Florestal e Agrícola (Imaflora)") | B49: =IFERROR(__xludf.DUMMYFUNCTION("""COMPUTED_VALUE"""),"Cerrado")
A50: =IFERROR(__xludf.DUMMYFUNCTION("""COMPUTED_VALUE"""),"Vale S.A.") | B50: =IFERROR(__xludf.DUMMYFUNCTION("""COMPUTED_VALUE"""),"Amazonia")
A51: =IFERROR(__xludf.DUMMYFUNCTION("""COMPUTED_VALUE"""),"Vale S.A.") | B51: =IFERROR(__xludf.DUMMYFUNCTION("""COMPUTED_VALUE"""),"Cerrado")
A52: =IFERROR(__xludf.DUMMYFUNCTION("""COMPUTED_VALUE"""),"Suzano S.A.") | B52: =IFERROR(__xludf.DUMMYFUNCTION("""COMPUTED_VALUE"""),"Amazonia")
A53: =IFERROR(__xludf.DUMMYFUNCTION("""COMPUTED_VALUE"""),"Suzano S.A.") | B53: =IFERROR(__xludf.DUMMYFUNCTION("""COMPUTED_VALUE"""),"Cerrado")
A54: =IFERROR(__xludf.DUMMYFUNCTION("""COMPUTED_VALUE"""),"Banco da Amazônia S.A. (BASA)") | B54: =IFERROR(__xludf.DUMMYFUNCTION("""COMPUTED_VALUE"""),"Amazonia")
A55: =IFERROR(__xludf.DUMMYFUNCTION("""COMPUTED_VALUE"""),"Instituto de Conservação e Desenvolvimento Sustentável da Amazônia (IDESAM)") | B55: =IFERROR(__xludf.DUMMYFUNCTION("""COMPUTED_VALUE"""),"Amazonia")
A56: =IFERROR(__xludf.DUMMYFUNCTION("""COMPUTED_VALUE"""),"Instituto Conexões Sustentáveis (Conexsus)") | B56: =IFERROR(__xludf.DUMMYFUNCTION("""COMPUTED_VALUE"""),"Amazonia")
A57: =IFERROR(__xludf.DUMMYFUNCTION("""COMPUTED_VALUE"""),"Instituto Conexões Sustentáveis (Conexsus)") | B57: =IFERROR(__xludf.DUMMYFUNCTION("""COMPUTED_VALUE"""),"Caatinga")
A58: =IFERROR(__xludf.DUMMYFUNCTION("""COMPUTED_VALUE"""),"Instituto Conexões Sustentáveis (Conexsus)") | B58: =IFERROR(__xludf.DUMMYFUNCTION("""COMPUTED_VALUE"""),"Cerrado")
A59: =IFERROR(__xludf.DUMMYFUNCTION("""COMPUTED_VALUE"""),"Fundação Grupo Boticário de Proteção à Natureza") | B59: =IFERROR(__xludf.DUMMYFUNCTION("""COMPUTED_VALUE"""),"Cerrado")
A60: =IFERROR(__xludf.DUMMYFUNCTION("""COMPUTED_VALUE"""),"Natura") | B60: =IFERROR(__xludf.DUMMYFUNCTION("""COMPUTED_VALUE"""),"Amazonia")
A61: =IFERROR(__xludf.DUMMYFUNCTION("""COMPUTED_VALUE"""),"Natura") | B61: =IFERROR(__xludf.DUMMYFUNCTION("""COMPUTED_VALUE"""),"Cerrado")
A62: =IFERROR(__xludf.DUMMYFUNCTION("""COMPUTED_VALUE"""),"Centro de Empreendedorismo da Amazônia (CEA)") | B62: =IFERROR(__xludf.DUMMYFUNCTION("""COMPUTED_VALUE"""),"Amazonia")
A63: =IFERROR(__xludf.DUMMYFUNCTION("""COMPUTED_VALUE"""),"Manioca") | B63: =IFERROR(__xludf.DUMMYFUNCTION("""COMPUTED_VALUE"""),"Amazonia")
A64: =IFERROR(__xludf.DUMMYFUNCTION("""COMPUTED_VALUE"""),"De Mendes") | B64: =IFERROR(__xludf.DUMMYFUNCTION("""COMPUTED_VALUE"""),"Amazonia")
A65: =IFERROR(__xludf.DUMMYFUNCTION("""COMPUTED_VALUE"""),"Climate and Land Use Alliance (CLUA)") | B65: =IFERROR(__xludf.DUMMYFUNCTION("""COMPUTED_VALUE"""),"Amazonia")
A66: =IFERROR(__xludf.DUMMYFUNCTION("""COMPUTED_VALUE"""),"Climate and Land Use Alliance (CLUA)") | B66: =IFERROR(__xludf.DUMMYFUNCTION("""COMPUTED_VALUE"""),"Cerrado")
A67: =IFERROR(__xludf.DUMMYFUNCTION("""COMPUTED_VALUE"""),"AMAZ") | B67: =IFERROR(__xludf.DUMMYFUNCTION("""COMPUTED_VALUE"""),"Amazonia")
A68: =IFERROR(__xludf.DUMMYFUNCTION("""COMPUTED_VALUE"""),"CocoaAction Brasil") | B68: =IFERROR(__xludf.DUMMYFUNCTION("""COMPUTED_VALUE"""),"Amazonia")
A69: =IFERROR(__xludf.DUMMYFUNCTION("""COMPUTED_VALUE"""),"Instituto de Pesquisas Ecológicas (IPÊ)") | B69: =IFERROR(__xludf.DUMMYFUNCTION("""COMPUTED_VALUE"""),"Amazonia")
A70: =IFERROR(__xludf.DUMMYFUNCTION("""COMPUTED_VALUE"""),"Fundação Nacional dos Povos Indígenas (FUNAI)") | B70: =IFERROR(__xludf.DUMMYFUNCTION("""COMPUTED_VALUE"""),"Amazonia")
A71: =IFERROR(__xludf.DUMMYFUNCTION("""COMPUTED_VALUE"""),"Fundação Nacional dos Povos Indígenas (FUNAI)") | B71: =IFERROR(__xludf.DUMMYFUNCTION("""COMPUTED_VALUE"""),"Caatinga")
A72: =IFERROR(__xludf.DUMMYFUNCTION("""COMPUTED_VALUE"""),"Fundação Nacional dos Povos Indígenas (FUNAI)") | B72: =IFERROR(__xludf.DUMMYFUNCTION("""COMPUTED_VALUE"""),"Cerrado")
A73: =IFERROR(__xludf.DUMMYFUNCTION("""COMPUTED_VALUE"""),"Gordon and Betty Moore Foundation") | B73: =IFERROR(__xludf.DUMMYFUNCTION("""COMPUTED_VALUE"""),"Amazonia")
A74: =IFERROR(__xludf.DUMMYFUNCTION("""COMPUTED_VALUE"""),"Instituto de Energia e Meio Ambiente (IEMA)") | B74: =IFERROR(__xludf.DUMMYFUNCTION("""COMPUTED_VALUE"""),"Amazonia")
A75: =IFERROR(__xludf.DUMMYFUNCTION("""COMPUTED_VALUE"""),"Instituto de Energia e Meio Ambiente (IEMA)") | B75: =IFERROR(__xludf.DUMMYFUNCTION("""COMPUTED_VALUE"""),"Caatinga")
A76: =IFERROR(__xludf.DUMMYFUNCTION("""COMPUTED_VALUE"""),"Instituto de Energia e Meio Ambiente (IEMA)") | B76: =IFERROR(__xludf.DUMMYFUNCTION("""COMPUTED_VALUE"""),"Cerrado")
A77: =IFERROR(__xludf.DUMMYFUNCTION("""COMPUTED_VALUE"""),"Instituto E+ Transição Energética (E+)") | B77: =IFERROR(__xludf.DUMMYFUNCTION("""COMPUTED_VALUE"""),"Amazonia")
A78: =IFERROR(__xludf.DUMMYFUNCTION("""COMPUTED_VALUE"""),"Instituto E+ Transição Energética (E+)") | B78: =IFERROR(__xludf.DUMMYFUNCTION("""COMPUTED_VALUE"""),"Caatinga")
A79: =IFERROR(__xludf.DUMMYFUNCTION("""COMPUTED_VALUE"""),"Agroicone") | B79: =IFERROR(__xludf.DUMMYFUNCTION("""COMPUTED_VALUE"""),"Amazonia")
A80: =IFERROR(__xludf.DUMMYFUNCTION("""COMPUTED_VALUE"""),"Agroicone") | B80: =IFERROR(__xludf.DUMMYFUNCTION("""COMPUTED_VALUE"""),"Cerrado")
A81: =IFERROR(__xludf.DUMMYFUNCTION("""COMPUTED_VALUE"""),"JBS") | B81: =IFERROR(__xludf.DUMMYFUNCTION("""COMPUTED_VALUE"""),"Amazonia")
A82: =IFERROR(__xludf.DUMMYFUNCTION("""COMPUTED_VALUE"""),"JBS") | B82: =IFERROR(__xludf.DUMMYFUNCTION("""COMPUTED_VALUE"""),"Cerrado")
A83: =IFERROR(__xludf.DUMMYFUNCTION("""COMPUTED_VALUE"""),"Marfrig") | B83: =IFERROR(__xludf.DUMMYFUNCTION("""COMPUTED_VALUE"""),"Amazonia")
A84: =IFERROR(__xludf.DUMMYFUNCTION("""COMPUTED_VALUE"""),"Marfrig") | B84: =IFERROR(__xludf.DUMMYFUNCTION("""COMPUTED_VALUE"""),"Cerrado")
A85: =IFERROR(__xludf.DUMMYFUNCTION("""COMPUTED_VALUE"""),"Amaggi") | B85: =IFERROR(__xludf.DUMMYFUNCTION("""COMPUTED_VALUE"""),"Amazonia")
A86: =IFERROR(__xludf.DUMMYFUNCTION("""COMPUTED_VALUE"""),"Amaggi") | B86: =IFERROR(__xludf.DUMMYFUNCTION("""COMPUTED_VALUE"""),"Cerrado")
A87: =IFERROR(__xludf.DUMMYFUNCTION("""COMPUTED_VALUE"""),"SLC Agrícola") | B87: =IFERROR(__xludf.DUMMYFUNCTION("""COMPUTED_VALUE"""),"Amazonia")
A88: =IFERROR(__xludf.DUMMYFUNCTION("""COMPUTED_VALUE"""),"SLC Agrícola") | B88: =IFERROR(__xludf.DUMMYFUNCTION("""COMPUTED_VALUE"""),"Cerrado")
A89: =IFERROR(__xludf.DUMMYFUNCTION("""COMPUTED_VALUE"""),"Instituto de Pesquisa Ambiental da Amazônia (IPAM)") | B89: =IFERROR(__xludf.DUMMYFUNCTION("""COMPUTED_VALUE"""),"Amazonia")
A90: =IFERROR(__xludf.DUMMYFUNCTION("""COMPUTED_VALUE"""),"Instituto de Pesquisa Ambiental da Amazônia (IPAM)") | B90: =IFERROR(__xludf.DUMMYFUNCTION("""COMPUTED_VALUE"""),"Cerrado")
A91: =IFERROR(__xludf.DUMMYFUNCTION("""COMPUTED_VALUE"""),"Global Canopy") | B91: =IFERROR(__xludf.DUMMYFUNCTION("""COMPUTED_VALUE"""),"Amazonia")
A92: =IFERROR(__xludf.DUMMYFUNCTION("""COMPUTED_VALUE"""),"Global Canopy") | B92: =IFERROR(__xludf.DUMMYFUNCTION("""COMPUTED_VALUE"""),"Cerrado")
A93: =IFERROR(__xludf.DUMMYFUNCTION("""COMPUTED_VALUE"""),"Good Energies Foundation") | B93: =IFERROR(__xludf.DUMMYFUNCTION("""COMPUTED_VALUE"""),"Amazonia")
A94: =IFERROR(__xludf.DUMMYFUNCTION("""COMPUTED_VALUE"""),"Carrefour Brasil") | B94: =IFERROR(__xludf.DUMMYFUNCTION("""COMPUTED_VALUE"""),"Amazonia")
A95: =IFERROR(__xludf.DUMMYFUNCTION("""COMPUTED_VALUE"""),"Carrefour Brasil") | B95: =IFERROR(__xludf.DUMMYFUNCTION("""COMPUTED_VALUE"""),"Cerrado")
A96: =IFERROR(__xludf.DUMMYFUNCTION("""COMPUTED_VALUE"""),"Nestlé Brasil") | B96: =IFERROR(__xludf.DUMMYFUNCTION("""COMPUTED_VALUE"""),"Cerrado")
A97: =IFERROR(__xludf.DUMMYFUNCTION("""COMPUTED_VALUE"""),"Serviço Florestal Brasileiro (SFB)") | B97: =IFERROR(__xludf.DUMMYFUNCTION("""COMPUTED_VALUE"""),"Amazonia")
A98: =IFERROR(__xludf.DUMMYFUNCTION("""COMPUTED_VALUE"""),"Serviço Florestal Brasileiro (SFB)") | B98: =IFERROR(__xludf.DUMMYFUNCTION("""COMPUTED_VALUE"""),"Cerrado")
A99: =IFERROR(__xludf.DUMMYFUNCTION("""COMPUTED_VALUE"""),"Klabin") | B99: =IFERROR(__xludf.DUMMYFUNCTION("""COMPUTED_VALUE"""),"Cerrado")
A100: =IFERROR(__xludf.DUMMYFUNCTION("""COMPUTED_VALUE"""),"Bracell") | B100: =IFERROR(__xludf.DUMMYFUNCTION("""COMPUTED_VALUE"""),"Cerrado")
...

Sheet Bride_Secondary_Biome
A1: =IFERROR(__xludf.DUMMYFUNCTION("ARRAYFORMULA(QUERY(SUBSTITUTE(SPLIT(FLATTEN(Data_Looker!B1:B339 & ""|"" & SPLIT(SUBSTITUTE(Data_Looker!I1:I339, ""Land, Food and Forest"", ""PROTEGER1""), "", "", FALSE)), ""|""), ""PROTEGER1"", ""Land, Food and Forest""), ""where Col2 <> ''""))"),"Stakeholder ") | B1: =IFERROR(__xludf.DUMMYFUNCTION("""COMPUTED_VALUE"""),"Secondary Territory lens (Biome) ")
A2: =IFERROR(__xludf.DUMMYFUNCTION("""COMPUTED_VALUE"""),"Fundo Brasileiro para a Biodiversidade (FUNBIO)") | B2: =IFERROR(__xludf.DUMMYFUNCTION("""COMPUTED_VALUE"""),"Mata&Atlântica")
A3: =IFERROR(__xludf.DUMMYFUNCTION("""COMPUTED_VALUE"""),"Fundo Brasileiro para a Biodiversidade (FUNBIO)") | B3: =IFERROR(__xludf.DUMMYFUNCTION("""COMPUTED_VALUE"""),"Pantanal")
A4: =IFERROR(__xludf.DUMMYFUNCTION("""COMPUTED_VALUE"""),"Fundo Brasileiro para a Biodiversidade (FUNBIO)") | B4: =IFERROR(__xludf.DUMMYFUNCTION("""COMPUTED_VALUE"""),"Pampa")
A5: =IFERROR(__xludf.DUMMYFUNCTION("""COMPUTED_VALUE"""),"Fundo Brasileiro para a Biodiversidade (FUNBIO)") | B5: =IFERROR(__xludf.DUMMYFUNCTION("""COMPUTED_VALUE"""),"Coastal&maritime")
A6: =IFERROR(__xludf.DUMMYFUNCTION("""COMPUTED_VALUE"""),"Instituto Clima e Sociedade (iCS)") | B6: =IFERROR(__xludf.DUMMYFUNCTION("""COMPUTED_VALUE"""),"Mata&Atlântica")
A7: =IFERROR(__xludf.DUMMYFUNCTION("""COMPUTED_VALUE"""),"Instituto Clima e Sociedade (iCS)") | B7: =IFERROR(__xludf.DUMMYFUNCTION("""COMPUTED_VALUE"""),"Pantanal")
A8: =IFERROR(__xludf.DUMMYFUNCTION("""COMPUTED_VALUE"""),"Instituto Clima e Sociedade (iCS)") | B8: =IFERROR(__xludf.DUMMYFUNCTION("""COMPUTED_VALUE"""),"Pampa")
A9: =IFERROR(__xludf.DUMMYFUNCTION("""COMPUTED_VALUE"""),"Instituto Clima e Sociedade (iCS)") | B9: =IFERROR(__xludf.DUMMYFUNCTION("""COMPUTED_VALUE"""),"Coastal&maritime")
A10: =IFERROR(__xludf.DUMMYFUNCTION("""COMPUTED_VALUE"""),"Instituto Ethos") | B10: =IFERROR(__xludf.DUMMYFUNCTION("""COMPUTED_VALUE"""),"Mata&Atlântica")
A11: =IFERROR(__xludf.DUMMYFUNCTION("""COMPUTED_VALUE"""),"Instituto Ethos") | B11: =IFERROR(__xludf.DUMMYFUNCTION("""COMPUTED_VALUE"""),"Pantanal")
A12: =IFERROR(__xludf.DUMMYFUNCTION("""COMPUTED_VALUE"""),"Instituto Ethos") | B12: =IFERROR(__xludf.DUMMYFUNCTION("""COMPUTED_VALUE"""),"Pampa")
A13: =IFERROR(__xludf.DUMMYFUNCTION("""COMPUTED_VALUE"""),"Instituto Ethos") | B13: =IFERROR(__xludf.DUMMYFUNCTION("""COMPUTED_VALUE"""),"Coastal&maritime")
A14: =IFERROR(__xludf.DUMMYFUNCTION("""COMPUTED_VALUE"""),"Instituto Climate Ventures Brasil (Climate Ventures)") | B14: =IFERROR(__xludf.DUMMYFUNCTION("""COMPUTED_VALUE"""),"Mata&Atlântica")
A15: =IFERROR(__xludf.DUMMYFUNCTION("""COMPUTED_VALUE"""),"Instituto Climate Ventures Brasil (Climate Ventures)") | B15: =IFERROR(__xludf.DUMMYFUNCTION("""COMPUTED_VALUE"""),"Pantanal")
A16: =IFERROR(__xludf.DUMMYFUNCTION("""COMPUTED_VALUE"""),"Instituto Climate Ventures Brasil (Climate Ventures)") | B16: =IFERROR(__xludf.DUMMYFUNCTION("""COMPUTED_VALUE"""),"Pampa")
A17: =IFERROR(__xludf.DUMMYFUNCTION("""COMPUTED_VALUE"""),"Instituto Climate Ventures Brasil (Climate Ventures)") | B17: =IFERROR(__xludf.DUMMYFUNCTION("""COMPUTED_VALUE"""),"Coastal&maritime")
A18: =IFERROR(__xludf.DUMMYFUNCTION("""COMPUTED_VALUE"""),"Fundação Tide Setúbal") | B18: =IFERROR(__xludf.DUMMYFUNCTION("""COMPUTED_VALUE"""),"Mata&Atlântica")
A19: =IFERROR(__xludf.DUMMYFUNCTION("""COMPUTED_VALUE"""),"Instituto Talanoa") | B19: =IFERROR(__xludf.DUMMYFUNCTION("""COMPUTED_VALUE"""),"Mata&Atlântica")
A20: =IFERROR(__xludf.DUMMYFUNCTION("""COMPUTED_VALUE"""),"Instituto Talanoa") | B20: =IFERROR(__xludf.DUMMYFUNCTION("""COMPUTED_VALUE"""),"Pantanal")
A21: =IFERROR(__xludf.DUMMYFUNCTION("""COMPUTED_VALUE"""),"Instituto Talanoa") | B21: =IFERROR(__xludf.DUMMYFUNCTION("""COMPUTED_VALUE"""),"Pampa")
A22: =IFERROR(__xludf.DUMMYFUNCTION("""COMPUTED_VALUE"""),"Instituto Talanoa") | B22: =IFERROR(__xludf.DUMMYFUNCTION("""COMPUTED_VALUE"""),"Coastal&maritime")
A23: =IFERROR(__xludf.DUMMYFUNCTION("""COMPUTED_VALUE"""),"Instituto Alana") | B23: =IFERROR(__xludf.DUMMYFUNCTION("""COMPUTED_VALUE"""),"Mata&Atlântica")
A24: =IFERROR(__xludf.DUMMYFUNCTION("""COMPUTED_VALUE"""),"Instituto Arapyaú") | B24: =IFERROR(__xludf.DUMMYFUNCTION("""COMPUTED_VALUE"""),"Mata&Atlântica")
A25: =IFERROR(__xludf.DUMMYFUNCTION("""COMPUTED_VALUE"""),"Instituto Semeia") | B25: =IFERROR(__xludf.DUMMYFUNCTION("""COMPUTED_VALUE"""),"Mata&Atlântica")
A26: =IFERROR(__xludf.DUMMYFUNCTION("""COMPUTED_VALUE"""),"Instituto Semeia") | B26: =IFERROR(__xludf.DUMMYFUNCTION("""COMPUTED_VALUE"""),"Pantanal")
A27: =IFERROR(__xludf.DUMMYFUNCTION("""COMPUTED_VALUE"""),"Instituto Semeia") | B27: =IFERROR(__xludf.DUMMYFUNCTION("""COMPUTED_VALUE"""),"Pampa")
A28: =IFERROR(__xludf.DUMMYFUNCTION("""COMPUTED_VALUE"""),"Instituto Semeia") | B28: =IFERROR(__xludf.DUMMYFUNCTION("""COMPUTED_VALUE"""),"Coastal&maritime")
A29: =IFERROR(__xludf.DUMMYFUNCTION("""COMPUTED_VALUE"""),"Alcoa") | B29: =IFERROR(__xludf.DUMMYFUNCTION("""COMPUTED_VALUE"""),"Coastal&maritime")
A30: =IFERROR(__xludf.DUMMYFUNCTION("""COMPUTED_VALUE"""),"Norsk Hydro ASA (Hydro)") | B30: =IFERROR(__xludf.DUMMYFUNCTION("""COMPUTED_VALUE"""),"Coastal&maritime")
A31: =IFERROR(__xludf.DUMMYFUNCTION("""COMPUTED_VALUE"""),"Instituto Socioambiental (ISA)") | B31: =IFERROR(__xludf.DUMMYFUNCTION("""COMPUTED_VALUE"""),"Mata&Atlântica")
A32: =IFERROR(__xludf.DUMMYFUNCTION("""COMPUTED_VALUE"""),"The Nature Conservancy Brasil (TNC Brasil)") | B32: =IFERROR(__xludf.DUMMYFUNCTION("""COMPUTED_VALUE"""),"Mata&Atlântica")
A33: =IFERROR(__xludf.DUMMYFUNCTION("""COMPUTED_VALUE"""),"The Nature Conservancy Brasil (TNC Brasil)") | B33: =IFERROR(__xludf.DUMMYFUNCTION("""COMPUTED_VALUE"""),"Coastal&maritime")
A34: =IFERROR(__xludf.DUMMYFUNCTION("""COMPUTED_VALUE"""),"Conservação Internacional Brasil (CI-Brasil)") | B34: =IFERROR(__xludf.DUMMYFUNCTION("""COMPUTED_VALUE"""),"Mata&Atlântica")
A35: =IFERROR(__xludf.DUMMYFUNCTION("""COMPUTED_VALUE"""),"Conservação Internacional Brasil (CI-Brasil)") | B35: =IFERROR(__xludf.DUMMYFUNCTION("""COMPUTED_VALUE"""),"Coastal&maritime")
A36: =IFERROR(__xludf.DUMMYFUNCTION("""COMPUTED_VALUE"""),"WWF-Brasil") | B36: =IFERROR(__xludf.DUMMYFUNCTION("""COMPUTED_VALUE"""),"Pantanal")
A37: =IFERROR(__xludf.DUMMYFUNCTION("""COMPUTED_VALUE"""),"WWF-Brasil") | B37: =IFERROR(__xludf.DUMMYFUNCTION("""COMPUTED_VALUE"""),"Mata&Atlântica")
A38: =IFERROR(__xludf.DUMMYFUNCTION("""COMPUTED_VALUE"""),"WRI Brasil") | B38: =IFERROR(__xludf.DUMMYFUNCTION("""COMPUTED_VALUE"""),"Mata&Atlântica")
A39: =IFERROR(__xludf.DUMMYFUNCTION("""COMPUTED_VALUE"""),"Fundação SOS Mata Atlântica") | B39: =IFERROR(__xludf.DUMMYFUNCTION("""COMPUTED_VALUE"""),"Mata&Atlântica")
A40: =IFERROR(__xludf.DUMMYFUNCTION("""COMPUTED_VALUE"""),"Empresa Brasileira de Pesquisa Agropecuária (Embrapa)") | B40: =IFERROR(__xludf.DUMMYFUNCTION("""COMPUTED_VALUE"""),"Mata&Atlântica")
A41: =IFERROR(__xludf.DUMMYFUNCTION("""COMPUTED_VALUE"""),"Empresa Brasileira de Pesquisa Agropecuária (Embrapa)") | B41: =IFERROR(__xludf.DUMMYFUNCTION("""COMPUTED_VALUE"""),"Pantanal")
A42: =IFERROR(__xludf.DUMMYFUNCTION("""COMPUTED_VALUE"""),"Empresa Brasileira de Pesquisa Agropecuária (Embrapa)") | B42: =IFERROR(__xludf.DUMMYFUNCTION("""COMPUTED_VALUE"""),"Pampa")
A43: =IFERROR(__xludf.DUMMYFUNCTION("""COMPUTED_VALUE"""),"Empresa Brasileira de Pesquisa Agropecuária (Embrapa)") | B43: =IFERROR(__xludf.DUMMYFUNCTION("""COMPUTED_VALUE"""),"Coastal&maritime")
A44: =IFERROR(__xludf.DUMMYFUNCTION("""COMPUTED_VALUE"""),"Instituto Brasileiro do Meio Ambiente e dos Recursos Naturais Renováveis (Ibama)") | B44: =IFERROR(__xludf.DUMMYFUNCTION("""COMPUTED_VALUE"""),"Mata&Atlântica")
A45: =IFERROR(__xludf.DUMMYFUNCTION("""COMPUTED_VALUE"""),"Instituto Brasileiro do Meio Ambiente e dos Recursos Naturais Renováveis (Ibama)") | B45: =IFERROR(__xludf.DUMMYFUNCTION("""COMPUTED_VALUE"""),"Pantanal")
A46: =IFERROR(__xludf.DUMMYFUNCTION("""COMPUTED_VALUE"""),"Instituto Brasileiro do Meio Ambiente e dos Recursos Naturais Renováveis (Ibama)") | B46: =IFERROR(__xludf.DUMMYFUNCTION("""COMPUTED_VALUE"""),"Pampa")
A47: =IFERROR(__xludf.DUMMYFUNCTION("""COMPUTED_VALUE"""),"Instituto Brasileiro do Meio Ambiente e dos Recursos Naturais Renováveis (Ibama)") | B47: =IFERROR(__xludf.DUMMYFUNCTION("""COMPUTED_VALUE"""),"Coastal&maritime")
A48: =IFERROR(__xludf.DUMMYFUNCTION("""COMPUTED_VALUE"""),"Instituto Chico Mendes de Conservação da Biodiversidade (ICMBio)") | B48: =IFERROR(__xludf.DUMMYFUNCTION("""COMPUTED_VALUE"""),"Mata&Atlântica")
A49: =IFERROR(__xludf.DUMMYFUNCTION("""COMPUTED_VALUE"""),"Instituto Chico Mendes de Conservação da Biodiversidade (ICMBio)") | B49: =IFERROR(__xludf.DUMMYFUNCTION("""COMPUTED_VALUE"""),"Pantanal")
A50: =IFERROR(__xludf.DUMMYFUNCTION("""COMPUTED_VALUE"""),"Instituto Chico Mendes de Conservação da Biodiversidade (ICMBio)") | B50: =IFERROR(__xludf.DUMMYFUNCTION("""COMPUTED_VALUE"""),"Pampa")
A51: =IFERROR(__xludf.DUMMYFUNCTION("""COMPUTED_VALUE"""),"Instituto Chico Mendes de Conservação da Biodiversidade (ICMBio)") | B51: =IFERROR(__xludf.DUMMYFUNCTION("""COMPUTED_VALUE"""),"Coastal&maritime")
A52: =IFERROR(__xludf.DUMMYFUNCTION("""COMPUTED_VALUE"""),"Instituto de Manejo e Certificação Florestal e Agrícola (Imaflora)") | B52: =IFERROR(__xludf.DUMMYFUNCTION("""COMPUTED_VALUE"""),"Mata&Atlântica")
A53: =IFERROR(__xludf.DUMMYFUNCTION("""COMPUTED_VALUE"""),"Instituto de Manejo e Certificação Florestal e Agrícola (Imaflora)") | B53: =IFERROR(__xludf.DUMMYFUNCTION("""COMPUTED_VALUE"""),"Pampa")
A54: =IFERROR(__xludf.DUMMYFUNCTION("""COMPUTED_VALUE"""),"Vale S.A.") | B54: =IFERROR(__xludf.DUMMYFUNCTION("""COMPUTED_VALUE"""),"Mata&Atlântica")
A55: =IFERROR(__xludf.DUMMYFUNCTION("""COMPUTED_VALUE"""),"Suzano S.A.") | B55: =IFERROR(__xludf.DUMMYFUNCTION("""COMPUTED_VALUE"""),"Mata&Atlântica")
A56: =IFERROR(__xludf.DUMMYFUNCTION("""COMPUTED_VALUE"""),"Instituto Conexões Sustentáveis (Conexsus)") | B56: =IFERROR(__xludf.DUMMYFUNCTION("""COMPUTED_VALUE"""),"Mata&Atlântica")
A57: =IFERROR(__xludf.DUMMYFUNCTION("""COMPUTED_VALUE"""),"Instituto Conexões Sustentáveis (Conexsus)") | B57: =IFERROR(__xludf.DUMMYFUNCTION("""COMPUTED_VALUE"""),"Pampa")
A58: =IFERROR(__xludf.DUMMYFUNCTION("""COMPUTED_VALUE"""),"Fundação Grupo Boticário de Proteção à Natureza") | B58: =IFERROR(__xludf.DUMMYFUNCTION("""COMPUTED_VALUE"""),"Mata&Atlântica")
A59: =IFERROR(__xludf.DUMMYFUNCTION("""COMPUTED_VALUE"""),"Natura") | B59: =IFERROR(__xludf.DUMMYFUNCTION("""COMPUTED_VALUE"""),"Mata&Atlântica")
A60: =IFERROR(__xludf.DUMMYFUNCTION("""COMPUTED_VALUE"""),"Natura") | B60: =IFERROR(__xludf.DUMMYFUNCTION("""COMPUTED_VALUE"""),"Pampa")
A61: =IFERROR(__xludf.DUMMYFUNCTION("""COMPUTED_VALUE"""),"Natura") | B61: =IFERROR(__xludf.DUMMYFUNCTION("""COMPUTED_VALUE"""),"Pantanal")
A62: =IFERROR(__xludf.DUMMYFUNCTION("""COMPUTED_VALUE"""),"CocoaAction Brasil") | B62: =IFERROR(__xludf.DUMMYFUNCTION("""COMPUTED_VALUE"""),"Mata&Atlântica")
A63: =IFERROR(__xludf.DUMMYFUNCTION("""COMPUTED_VALUE"""),"Instituto de Pesquisas Ecológicas (IPÊ)") | B63: =IFERROR(__xludf.DUMMYFUNCTION("""COMPUTED_VALUE"""),"Mata&Atlântica")
A64: =IFERROR(__xludf.DUMMYFUNCTION("""COMPUTED_VALUE"""),"Instituto de Pesquisas Ecológicas (IPÊ)") | B64: =IFERROR(__xludf.DUMMYFUNCTION("""COMPUTED_VALUE"""),"Pantanal")
A65: =IFERROR(__xludf.DUMMYFUNCTION("""COMPUTED_VALUE"""),"Fundação Nacional dos Povos Indígenas (FUNAI)") | B65: =IFERROR(__xludf.DUMMYFUNCTION("""COMPUTED_VALUE"""),"Mata&Atlântica")
A66: =IFERROR(__xludf.DUMMYFUNCTION("""COMPUTED_VALUE"""),"Fundação Nacional dos Povos Indígenas (FUNAI)") | B66: =IFERROR(__xludf.DUMMYFUNCTION("""COMPUTED_VALUE"""),"Pantanal")
A67: =IFERROR(__xludf.DUMMYFUNCTION("""COMPUTED_VALUE"""),"Fundação Nacional dos Povos Indígenas (FUNAI)") | B67: =IFERROR(__xludf.DUMMYFUNCTION("""COMPUTED_VALUE"""),"Pampa")
A68: =IFERROR(__xludf.DUMMYFUNCTION("""COMPUTED_VALUE"""),"Fundação Nacional dos Povos Indígenas (FUNAI)") | B68: =IFERROR(__xludf.DUMMYFUNCTION("""COMPUTED_VALUE"""),"Coastal&maritime")
A69: =IFERROR(__xludf.DUMMYFUNCTION("""COMPUTED_VALUE"""),"Instituto de Energia e Meio Ambiente (IEMA)") | B69: =IFERROR(__xludf.DUMMYFUNCTION("""COMPUTED_VALUE"""),"Mata&Atlântica")
A70: =IFERROR(__xludf.DUMMYFUNCTION("""COMPUTED_VALUE"""),"Instituto de Energia e Meio Ambiente (IEMA)") | B70: =IFERROR(__xludf.DUMMYFUNCTION("""COMPUTED_VALUE"""),"Pantanal")
A71: =IFERROR(__xludf.DUMMYFUNCTION("""COMPUTED_VALUE"""),"Instituto E+ Transição Energética (E+)") | B71: =IFERROR(__xludf.DUMMYFUNCTION("""COMPUTED_VALUE"""),"Mata&Atlântica")
A72: =IFERROR(__xludf.DUMMYFUNCTION("""COMPUTED_VALUE"""),"JBS") | B72: =IFERROR(__xludf.DUMMYFUNCTION("""COMPUTED_VALUE"""),"Pantanal")
A73: =IFERROR(__xludf.DUMMYFUNCTION("""COMPUTED_VALUE"""),"Marfrig") | B73: =IFERROR(__xludf.DUMMYFUNCTION("""COMPUTED_VALUE"""),"Pantanal")
A74: =IFERROR(__xludf.DUMMYFUNCTION("""COMPUTED_VALUE"""),"Amaggi") | B74: =IFERROR(__xludf.DUMMYFUNCTION("""COMPUTED_VALUE"""),"Pantanal")
A75: =IFERROR(__xludf.DUMMYFUNCTION("""COMPUTED_VALUE"""),"SLC Agrícola") | B75: =IFERROR(__xludf.DUMMYFUNCTION("""COMPUTED_VALUE"""),"Pantanal")
A76: =IFERROR(__xludf.DUMMYFUNCTION("""COMPUTED_VALUE"""),"Good Energies Foundation") | B76: =IFERROR(__xludf.DUMMYFUNCTION("""COMPUTED_VALUE"""),"Mata&Atlântica")
A77: =IFERROR(__xludf.DUMMYFUNCTION("""COMPUTED_VALUE"""),"Nestlé Brasil") | B77: =IFERROR(__xludf.DUMMYFUNCTION("""COMPUTED_VALUE"""),"Mata&Atlântica")
A78: =IFERROR(__xludf.DUMMYFUNCTION("""COMPUTED_VALUE"""),"Serviço Florestal Brasileiro (SFB)") | B78: =IFERROR(__xludf.DUMMYFUNCTION("""COMPUTED_VALUE"""),"Mata&Atlântica")
A79: =IFERROR(__xludf.DUMMYFUNCTION("""COMPUTED_VALUE"""),"Klabin") | B79: =IFERROR(__xludf.DUMMYFUNCTION("""COMPUTED_VALUE"""),"Mata&Atlântica")
A80: =IFERROR(__xludf.DUMMYFUNCTION("""COMPUTED_VALUE"""),"Rainforest Alliance") | B80: =IFERROR(__xludf.DUMMYFUNCTION("""COMPUTED_VALUE"""),"Mata&Atlântica")
A81: =IFERROR(__xludf.DUMMYFUNCTION("""COMPUTED_VALUE"""),"Consórcio Nordeste") | B81: =IFERROR(__xludf.DUMMYFUNCTION("""COMPUTED_VALUE"""),"Coastal&maritime")
A82: =IFERROR(__xludf.DUMMYFUNCTION("""COMPUTED_VALUE"""),"Consórcio Nordeste") | B82: =IFERROR(__xludf.DUMMYFUNCTION("""COMPUTED_VALUE"""),"Mata&Atlântica")
A83: =IFERROR(__xludf.DUMMYFUNCTION("""COMPUTED_VALUE"""),"Associação Brasileira de Energia Eólica (ABEEólica)") | B83: =IFERROR(__xludf.DUMMYFUNCTION("""COMPUTED_VALUE"""),"Coastal&maritime")
A84: =IFERROR(__xludf.DUMMYFUNCTION("""COMPUTED_VALUE"""),"Superintendência do Desenvolvimento do Nordeste (SUDENE)") | B84: =IFERROR(__xludf.DUMMYFUNCTION("""COMPUTED_VALUE"""),"Coastal&maritime")
A85: =IFERROR(__xludf.DUMMYFUNCTION("""COMPUTED_VALUE"""),"Superintendência do Desenvolvimento do Nordeste (SUDENE)") | B85: =IFERROR(__xludf.DUMMYFUNCTION("""COMPUTED_VALUE"""),"Mata&Atlântica")
A86: =IFERROR(__xludf.DUMMYFUNCTION("""COMPUTED_VALUE"""),"Casa dos Ventos") | B86: =IFERROR(__xludf.DUMMYFUNCTION("""COMPUTED_VALUE"""),"Coastal&maritime")
A87: =IFERROR(__xludf.DUMMYFUNCTION("""COMPUTED_VALUE"""),"Voltalia Energia do Brasil (Voltalia)") | B87: =IFERROR(__xludf.DUMMYFUNCTION("""COMPUTED_VALUE"""),"Coastal&maritime")
A88: =IFERROR(__xludf.DUMMYFUNCTION("""COMPUTED_VALUE"""),"Complexo Industrial Portuário de Suape (Suape)") | B88: =IFERROR(__xludf.DUMMYFUNCTION("""COMPUTED_VALUE"""),"Coastal&maritime")
A89: =IFERROR(__xludf.DUMMYFUNCTION("""COMPUTED_VALUE"""),"Complexo do Pecém (CIPP S.A.)") | B89: =IFERROR(__xludf.DUMMYFUNCTION("""COMPUTED_VALUE"""),"Coastal&maritime")
A90: =IFERROR(__xludf.DUMMYFUNCTION("""COMPUTED_VALUE"""),"Câmara Setorial de Energias Renováveis do Ceará (CS Renováveis/CE)") | B90: =IFERROR(__xludf.DUMMYFUNCTION("""COMPUTED_VALUE"""),"Coastal&maritime")
A91: =IFERROR(__xludf.DUMMYFUNCTION("""COMPUTED_VALUE"""),"AS-PTA – Agricultura Familiar e Agroecologia (AS-PTA)") | B91: =IFERROR(__xludf.DUMMYFUNCTION("""COMPUTED_VALUE"""),"Mata&Atlântica")
A92: =IFERROR(__xludf.DUMMYFUNCTION("""COMPUTED_VALUE"""),"Instituto Nacional de Pesquisas Espaciais (INPE)") | B92: =IFERROR(__xludf.DUMMYFUNCTION("""COMPUTED_VALUE"""),"Mata&Atlântica")
A93: =IFERROR(__xludf.DUMMYFUNCTION("""COMPUTED_VALUE"""),"Instituto Nacional de Pesquisas Espaciais (INPE)") | B93: =IFERROR(__xludf.DUMMYFUNCTION("""COMPUTED_VALUE"""),"Pantanal")
A94: =IFERROR(__xludf.DUMMYFUNCTION("""COMPUTED_VALUE"""),"Instituto Nacional de Pesquisas Espaciais (INPE)") | B94: =IFERROR(__xludf.DUMMYFUNCTION("""COMPUTED_VALUE"""),"Pampa")
A95: =IFERROR(__xludf.DUMMYFUNCTION("""COMPUTED_VALUE"""),"Instituto Nacional de Pesquisas Espaciais (INPE)") | B95: =IFERROR(__xludf.DUMMYFUNCTION("""COMPUTED_VALUE"""),"Coastal&maritime")
A96: =IFERROR(__xludf.DUMMYFUNCTION("""COMPUTED_VALUE"""),"Coalizão Brasil Clima, Florestas e Agricultura") | B96: =IFERROR(__xludf.DUMMYFUNCTION("""COMPUTED_VALUE"""),"Mata&Atlântica")
A97: =IFERROR(__xludf.DUMMYFUNCTION("""COMPUTED_VALUE"""),"Coalizão Brasil Clima, Florestas e Agricultura") | B97: =IFERROR(__xludf.DUMMYFUNCTION("""COMPUTED_VALUE"""),"Pantanal")
A98: =IFERROR(__xludf.DUMMYFUNCTION("""COMPUTED_VALUE"""),"Centro Internacional de Pesquisa Florestal e Agroflorestal (CIFOR-ICRAF)") | B98: =IFERROR(__xludf.DUMMYFUNCTION("""COMPUTED_VALUE"""),"Mata&Atlântica")
A99: =IFERROR(__xludf.DUMMYFUNCTION("""COMPUTED_VALUE"""),"Fundo Constitucional de Financiamento do Nordeste (FNE)") | B99: =IFERROR(__xludf.DUMMYFUNCTION("""COMPUTED_VALUE"""),"Coastal&maritime")
A100: =IFERROR(__xludf.DUMMYFUNCTION("""COMPUTED_VALUE"""),"Banco do Nordeste (BNB)") | B100: =IFERROR(__xludf.DUMMYFUNCTION("""COMPUTED_VALUE"""),"Coastal&maritime")
...

Sheet Bridge_Role_Ecosystem
A1: Stakeholder | B1: Role within the ecosystem
A2: =IFERROR(__xludf.DUMMYFUNCTION("ARRAYFORMULA( QUERY( SPLIT( FLATTEN( Data_Looker!B2:B340 & ""♦"" & TRIM( SPLIT( REGEXREPLACE(Data_Looker!K2:K340, ""\s*(,|;|\n)\s*"", ""♣""), ""♣"" ) ) ), ""♦"" "&" ), ""where Col2 is not null and Col2 <> ''"", 0 ) ) "),"Instituto Ibirapitanga") | B2: =IFERROR(__xludf.DUMMYFUNCTION("""COMPUTED_VALUE"""),"Funder")
A3: =IFERROR(__xludf.DUMMYFUNCTION("""COMPUTED_VALUE"""),"Instituto Ibirapitanga") | B3: =IFERROR(__xludf.DUMMYFUNCTION("""COMPUTED_VALUE"""),"Strategic partner")
A4: =IFERROR(__xludf.DUMMYFUNCTION("""COMPUTED_VALUE"""),"Instituto Serrapilheira") | B4: =IFERROR(__xludf.DUMMYFUNCTION("""COMPUTED_VALUE"""),"Funder")
A5: =IFERROR(__xludf.DUMMYFUNCTION("""COMPUTED_VALUE"""),"Instituto Serrapilheira") | B5: =IFERROR(__xludf.DUMMYFUNCTION("""COMPUTED_VALUE"""),"Technical assistance / research")
A6: =IFERROR(__xludf.DUMMYFUNCTION("""COMPUTED_VALUE"""),"Instituto Serrapilheira") | B6: =IFERROR(__xludf.DUMMYFUNCTION("""COMPUTED_VALUE"""),"Strategic partner")
A7: =IFERROR(__xludf.DUMMYFUNCTION("""COMPUTED_VALUE"""),"Fundo Brasileiro para a Biodiversidade (FUNBIO)") | B7: =IFERROR(__xludf.DUMMYFUNCTION("""COMPUTED_VALUE"""),"Funder")
A8: =IFERROR(__xludf.DUMMYFUNCTION("""COMPUTED_VALUE"""),"Fundo Brasileiro para a Biodiversidade (FUNBIO)") | B8: =IFERROR(__xludf.DUMMYFUNCTION("""COMPUTED_VALUE"""),"Capital provider / Financial intermediary")
A9: =IFERROR(__xludf.DUMMYFUNCTION("""COMPUTED_VALUE"""),"Instituto Clima e Sociedade (iCS)") | B9: =IFERROR(__xludf.DUMMYFUNCTION("""COMPUTED_VALUE"""),"Funder")
A10: =IFERROR(__xludf.DUMMYFUNCTION("""COMPUTED_VALUE"""),"Instituto Clima e Sociedade (iCS)") | B10: =IFERROR(__xludf.DUMMYFUNCTION("""COMPUTED_VALUE"""),"Strategic partner")
A11: =IFERROR(__xludf.DUMMYFUNCTION("""COMPUTED_VALUE"""),"Instituto Clima e Sociedade (iCS)") | B11: =IFERROR(__xludf.DUMMYFUNCTION("""COMPUTED_VALUE"""),"Convenor/enablers")
A12: =IFERROR(__xludf.DUMMYFUNCTION("""COMPUTED_VALUE"""),"Instituto Clima e Sociedade (iCS)") | B12: =IFERROR(__xludf.DUMMYFUNCTION("""COMPUTED_VALUE"""),"Capital provider / Financial intermediary")
A13: =IFERROR(__xludf.DUMMYFUNCTION("""COMPUTED_VALUE"""),"Instituto Cultura, Comunicação e Incidência (ICCI)") | B13: =IFERROR(__xludf.DUMMYFUNCTION("""COMPUTED_VALUE"""),"Project developer / Implementer")
A14: =IFERROR(__xludf.DUMMYFUNCTION("""COMPUTED_VALUE"""),"Instituto Cultura, Comunicação e Incidência (ICCI)") | B14: =IFERROR(__xludf.DUMMYFUNCTION("""COMPUTED_VALUE"""),"Policy influence / regulation")
A15: =IFERROR(__xludf.DUMMYFUNCTION("""COMPUTED_VALUE"""),"Grupo de Institutos, Fundações e Empresas (GIFE)") | B15: =IFERROR(__xludf.DUMMYFUNCTION("""COMPUTED_VALUE"""),"Convenor/enablers")
A16: =IFERROR(__xludf.DUMMYFUNCTION("""COMPUTED_VALUE"""),"Movimento Bem Maior (MBM)") | B16: =IFERROR(__xludf.DUMMYFUNCTION("""COMPUTED_VALUE"""),"Funder")
A17: =IFERROR(__xludf.DUMMYFUNCTION("""COMPUTED_VALUE"""),"Movimento Bem Maior (MBM)") | B17: =IFERROR(__xludf.DUMMYFUNCTION("""COMPUTED_VALUE"""),"Convenor/enablers")
A18: =IFERROR(__xludf.DUMMYFUNCTION("""COMPUTED_VALUE"""),"Instituto Beija ") | B18: =IFERROR(__xludf.DUMMYFUNCTION("""COMPUTED_VALUE"""),"Funder")
A19: =IFERROR(__xludf.DUMMYFUNCTION("""COMPUTED_VALUE"""),"Instituto Beija ") | B19: =IFERROR(__xludf.DUMMYFUNCTION("""COMPUTED_VALUE"""),"Convenor/enablers")
A20: =IFERROR(__xludf.DUMMYFUNCTION("""COMPUTED_VALUE"""),"Open Society Foundations") | B20: =IFERROR(__xludf.DUMMYFUNCTION("""COMPUTED_VALUE"""),"Funder")
A21: =IFERROR(__xludf.DUMMYFUNCTION("""COMPUTED_VALUE"""),"Open Society Foundations") | B21: =IFERROR(__xludf.DUMMYFUNCTION("""COMPUTED_VALUE"""),"Strategic partner")
A22: =IFERROR(__xludf.DUMMYFUNCTION("""COMPUTED_VALUE"""),"Instituto Ethos") | B22: =IFERROR(__xludf.DUMMYFUNCTION("""COMPUTED_VALUE"""),"Convenor/enablers")
A23: =IFERROR(__xludf.DUMMYFUNCTION("""COMPUTED_VALUE"""),"Instituto Ethos") | B23: =IFERROR(__xludf.DUMMYFUNCTION("""COMPUTED_VALUE"""),"Policy influence / regulation")
A24: =IFERROR(__xludf.DUMMYFUNCTION("""COMPUTED_VALUE"""),"Instituto para o Desenvolvimento do Investimento Social (IDIS)") | B24: =IFERROR(__xludf.DUMMYFUNCTION("""COMPUTED_VALUE"""),"Technical assistance / research")
A25: =IFERROR(__xludf.DUMMYFUNCTION("""COMPUTED_VALUE"""),"Instituto para o Desenvolvimento do Investimento Social (IDIS)") | B25: =IFERROR(__xludf.DUMMYFUNCTION("""COMPUTED_VALUE"""),"Convenor/enablers")
A26: =IFERROR(__xludf.DUMMYFUNCTION("""COMPUTED_VALUE"""),"Instituto Climate Ventures Brasil (Climate Ventures)") | B26: =IFERROR(__xludf.DUMMYFUNCTION("""COMPUTED_VALUE"""),"Convenor/enablers")
A27: =IFERROR(__xludf.DUMMYFUNCTION("""COMPUTED_VALUE"""),"Instituto Climate Ventures Brasil (Climate Ventures)") | B27: =IFERROR(__xludf.DUMMYFUNCTION("""COMPUTED_VALUE"""),"Project developer / Implementer")
A28: =IFERROR(__xludf.DUMMYFUNCTION("""COMPUTED_VALUE"""),"The Climate Group") | B28: =IFERROR(__xludf.DUMMYFUNCTION("""COMPUTED_VALUE"""),"Convenor/enablers")
A29: =IFERROR(__xludf.DUMMYFUNCTION("""COMPUTED_VALUE"""),"The Climate Group") | B29: =IFERROR(__xludf.DUMMYFUNCTION("""COMPUTED_VALUE"""),"Strategic partner")
A30: =IFERROR(__xludf.DUMMYFUNCTION("""COMPUTED_VALUE"""),"Fundação Maria Cecilia Souto Vidigal") | B30: =IFERROR(__xludf.DUMMYFUNCTION("""COMPUTED_VALUE"""),"Funder")
A31: =IFERROR(__xludf.DUMMYFUNCTION("""COMPUTED_VALUE"""),"Fundação Maria Cecilia Souto Vidigal") | B31: =IFERROR(__xludf.DUMMYFUNCTION("""COMPUTED_VALUE"""),"Strategic partner")
A32: =IFERROR(__xludf.DUMMYFUNCTION("""COMPUTED_VALUE"""),"Fundação Tide Setúbal") | B32: =IFERROR(__xludf.DUMMYFUNCTION("""COMPUTED_VALUE"""),"Funder")
A33: =IFERROR(__xludf.DUMMYFUNCTION("""COMPUTED_VALUE"""),"Fundação Tide Setúbal") | B33: =IFERROR(__xludf.DUMMYFUNCTION("""COMPUTED_VALUE"""),"Territorial anchor")
A34: =IFERROR(__xludf.DUMMYFUNCTION("""COMPUTED_VALUE"""),"Fundação Arymax") | B34: =IFERROR(__xludf.DUMMYFUNCTION("""COMPUTED_VALUE"""),"Funder")
A35: =IFERROR(__xludf.DUMMYFUNCTION("""COMPUTED_VALUE"""),"Fundação Arymax") | B35: =IFERROR(__xludf.DUMMYFUNCTION("""COMPUTED_VALUE"""),"Strategic partner")
A36: =IFERROR(__xludf.DUMMYFUNCTION("""COMPUTED_VALUE"""),"Instituto Talanoa") | B36: =IFERROR(__xludf.DUMMYFUNCTION("""COMPUTED_VALUE"""),"Technical assistance / research")
A37: =IFERROR(__xludf.DUMMYFUNCTION("""COMPUTED_VALUE"""),"Instituto Talanoa") | B37: =IFERROR(__xludf.DUMMYFUNCTION("""COMPUTED_VALUE"""),"Policy influence / regulation")
A38: =IFERROR(__xludf.DUMMYFUNCTION("""COMPUTED_VALUE"""),"Instituto Alana") | B38: =IFERROR(__xludf.DUMMYFUNCTION("""COMPUTED_VALUE"""),"Funder")
A39: =IFERROR(__xludf.DUMMYFUNCTION("""COMPUTED_VALUE"""),"Instituto Alana") | B39: =IFERROR(__xludf.DUMMYFUNCTION("""COMPUTED_VALUE"""),"Policy influence / regulation")
A40: =IFERROR(__xludf.DUMMYFUNCTION("""COMPUTED_VALUE"""),"Instituto Alana") | B40: =IFERROR(__xludf.DUMMYFUNCTION("""COMPUTED_VALUE"""),"Strategic partner")
A41: =IFERROR(__xludf.DUMMYFUNCTION("""COMPUTED_VALUE"""),"Instituto Alana") | B41: =IFERROR(__xludf.DUMMYFUNCTION("""COMPUTED_VALUE"""),"Community legitimacy / proximate leadership")
A42: =IFERROR(__xludf.DUMMYFUNCTION("""COMPUTED_VALUE"""),"Itaúsa (Itaúsa S.A.)") | B42: =IFERROR(__xludf.DUMMYFUNCTION("""COMPUTED_VALUE"""),"Strategic partner")
A43: =IFERROR(__xludf.DUMMYFUNCTION("""COMPUTED_VALUE"""),"Itaúsa (Itaúsa S.A.)") | B43: =IFERROR(__xludf.DUMMYFUNCTION("""COMPUTED_VALUE"""),"Capital provider / Financial intermediary")
A44: =IFERROR(__xludf.DUMMYFUNCTION("""COMPUTED_VALUE"""),"Instituto Arapyaú") | B44: =IFERROR(__xludf.DUMMYFUNCTION("""COMPUTED_VALUE"""),"Funder")
A45: =IFERROR(__xludf.DUMMYFUNCTION("""COMPUTED_VALUE"""),"Instituto Arapyaú") | B45: =IFERROR(__xludf.DUMMYFUNCTION("""COMPUTED_VALUE"""),"Strategic partner")
A46: =IFERROR(__xludf.DUMMYFUNCTION("""COMPUTED_VALUE"""),"Instituto Arapyaú") | B46: =IFERROR(__xludf.DUMMYFUNCTION("""COMPUTED_VALUE"""),"Territorial anchor")
A47: =IFERROR(__xludf.DUMMYFUNCTION("""COMPUTED_VALUE"""),"Instituto Semeia") | B47: =IFERROR(__xludf.DUMMYFUNCTION("""COMPUTED_VALUE"""),"Technical assistance / research")
A48: =IFERROR(__xludf.DUMMYFUNCTION("""COMPUTED_VALUE"""),"Instituto Semeia") | B48: =IFERROR(__xludf.DUMMYFUNCTION("""COMPUTED_VALUE"""),"Project developer / Implementer")
A49: =IFERROR(__xludf.DUMMYFUNCTION("""COMPUTED_VALUE"""),"Instituto Semeia") | B49: =IFERROR(__xludf.DUMMYFUNCTION("""COMPUTED_VALUE"""),"Funder")
A50: =IFERROR(__xludf.DUMMYFUNCTION("""COMPUTED_VALUE"""),"The David and Lucile Packard Foundation") | B50: =IFERROR(__xludf.DUMMYFUNCTION("""COMPUTED_VALUE"""),"Funder")
A51: =IFERROR(__xludf.DUMMYFUNCTION("""COMPUTED_VALUE"""),"The David and Lucile Packard Foundation") | B51: =IFERROR(__xludf.DUMMYFUNCTION("""COMPUTED_VALUE"""),"Strategic partner")
A52: =IFERROR(__xludf.DUMMYFUNCTION("""COMPUTED_VALUE"""),"Alcoa") | B52: =IFERROR(__xludf.DUMMYFUNCTION("""COMPUTED_VALUE"""),"Strategic partner")
A53: =IFERROR(__xludf.DUMMYFUNCTION("""COMPUTED_VALUE"""),"Alcoa") | B53: =IFERROR(__xludf.DUMMYFUNCTION("""COMPUTED_VALUE"""),"Implementation capacity (delivery)")
A54: =IFERROR(__xludf.DUMMYFUNCTION("""COMPUTED_VALUE"""),"Norsk Hydro ASA (Hydro)") | B54: =IFERROR(__xludf.DUMMYFUNCTION("""COMPUTED_VALUE"""),"Strategic partner")
A55: =IFERROR(__xludf.DUMMYFUNCTION("""COMPUTED_VALUE"""),"Norsk Hydro ASA (Hydro)") | B55: =IFERROR(__xludf.DUMMYFUNCTION("""COMPUTED_VALUE"""),"Implementation capacity (delivery)")
A56: =IFERROR(__xludf.DUMMYFUNCTION("""COMPUTED_VALUE"""),"Instituto Socioambiental (ISA)") | B56: =IFERROR(__xludf.DUMMYFUNCTION("""COMPUTED_VALUE"""),"Project developer / Implementer")
A57: =IFERROR(__xludf.DUMMYFUNCTION("""COMPUTED_VALUE"""),"Instituto Socioambiental (ISA)") | B57: =IFERROR(__xludf.DUMMYFUNCTION("""COMPUTED_VALUE"""),"Community legitimacy / proximate leadership")
A58: =IFERROR(__xludf.DUMMYFUNCTION("""COMPUTED_VALUE"""),"The Nature Conservancy Brasil (TNC Brasil)") | B58: =IFERROR(__xludf.DUMMYFUNCTION("""COMPUTED_VALUE"""),"Strategic partner")
A59: =IFERROR(__xludf.DUMMYFUNCTION("""COMPUTED_VALUE"""),"The Nature Conservancy Brasil (TNC Brasil)") | B59: =IFERROR(__xludf.DUMMYFUNCTION("""COMPUTED_VALUE"""),"Project developer / Implementer")
A60: =IFERROR(__xludf.DUMMYFUNCTION("""COMPUTED_VALUE"""),"Conservação Internacional Brasil (CI-Brasil)") | B60: =IFERROR(__xludf.DUMMYFUNCTION("""COMPUTED_VALUE"""),"Strategic partner")
A61: =IFERROR(__xludf.DUMMYFUNCTION("""COMPUTED_VALUE"""),"Conservação Internacional Brasil (CI-Brasil)") | B61: =IFERROR(__xludf.DUMMYFUNCTION("""COMPUTED_VALUE"""),"Project developer / Implementer")
A62: =IFERROR(__xludf.DUMMYFUNCTION("""COMPUTED_VALUE"""),"WWF-Brasil") | B62: =IFERROR(__xludf.DUMMYFUNCTION("""COMPUTED_VALUE"""),"Strategic partner")
A63: =IFERROR(__xludf.DUMMYFUNCTION("""COMPUTED_VALUE"""),"WWF-Brasil") | B63: =IFERROR(__xludf.DUMMYFUNCTION("""COMPUTED_VALUE"""),"Project developer / Implementer")
A64: =IFERROR(__xludf.DUMMYFUNCTION("""COMPUTED_VALUE"""),"WWF-Brasil") | B64: =IFERROR(__xludf.DUMMYFUNCTION("""COMPUTED_VALUE"""),"Policy influence / regulation")
A65: =IFERROR(__xludf.DUMMYFUNCTION("""COMPUTED_VALUE"""),"WRI Brasil") | B65: =IFERROR(__xludf.DUMMYFUNCTION("""COMPUTED_VALUE"""),"Strategic partner")
A66: =IFERROR(__xludf.DUMMYFUNCTION("""COMPUTED_VALUE"""),"WRI Brasil") | B66: =IFERROR(__xludf.DUMMYFUNCTION("""COMPUTED_VALUE"""),"Technical assistance / research")
A67: =IFERROR(__xludf.DUMMYFUNCTION("""COMPUTED_VALUE"""),"WRI Brasil") | B67: =IFERROR(__xludf.DUMMYFUNCTION("""COMPUTED_VALUE"""),"Policy influence / regulation")
A68: =IFERROR(__xludf.DUMMYFUNCTION("""COMPUTED_VALUE"""),"Fundação SOS Mata Atlântica") | B68: =IFERROR(__xludf.DUMMYFUNCTION("""COMPUTED_VALUE"""),"Policy influence / regulation")
A69: =IFERROR(__xludf.DUMMYFUNCTION("""COMPUTED_VALUE"""),"Fundação SOS Mata Atlântica") | B69: =IFERROR(__xludf.DUMMYFUNCTION("""COMPUTED_VALUE"""),"Implementation capacity (delivery)")
A70: =IFERROR(__xludf.DUMMYFUNCTION("""COMPUTED_VALUE"""),"Empresa Brasileira de Pesquisa Agropecuária (Embrapa)") | B70: =IFERROR(__xludf.DUMMYFUNCTION("""COMPUTED_VALUE"""),"Technical assistance / research")
A71: =IFERROR(__xludf.DUMMYFUNCTION("""COMPUTED_VALUE"""),"Empresa Brasileira de Pesquisa Agropecuária (Embrapa)") | B71: =IFERROR(__xludf.DUMMYFUNCTION("""COMPUTED_VALUE"""),"Territorial anchor")
A72: =IFERROR(__xludf.DUMMYFUNCTION("""COMPUTED_VALUE"""),"Sistema S") | B72: =IFERROR(__xludf.DUMMYFUNCTION("""COMPUTED_VALUE"""),"Implementation capacity (delivery)")
A73: =IFERROR(__xludf.DUMMYFUNCTION("""COMPUTED_VALUE"""),"Sistema S") | B73: =IFERROR(__xludf.DUMMYFUNCTION("""COMPUTED_VALUE"""),"Technical assistance / research")
A74: =IFERROR(__xludf.DUMMYFUNCTION("""COMPUTED_VALUE"""),"Instituto Brasileiro do Meio Ambiente e dos Recursos Naturais Renováveis (Ibama)") | B74: =IFERROR(__xludf.DUMMYFUNCTION("""COMPUTED_VALUE"""),"Policy influence / regulation")
A75: =IFERROR(__xludf.DUMMYFUNCTION("""COMPUTED_VALUE"""),"Instituto Brasileiro do Meio Ambiente e dos Recursos Naturais Renováveis (Ibama)") | B75: =IFERROR(__xludf.DUMMYFUNCTION("""COMPUTED_VALUE"""),"Territorial anchor")
A76: =IFERROR(__xludf.DUMMYFUNCTION("""COMPUTED_VALUE"""),"Instituto Chico Mendes de Conservação da Biodiversidade (ICMBio)") | B76: =IFERROR(__xludf.DUMMYFUNCTION("""COMPUTED_VALUE"""),"Policy influence / regulation")
A77: =IFERROR(__xludf.DUMMYFUNCTION("""COMPUTED_VALUE"""),"Instituto Chico Mendes de Conservação da Biodiversidade (ICMBio)") | B77: =IFERROR(__xludf.DUMMYFUNCTION("""COMPUTED_VALUE"""),"Territorial anchor")
A78: =IFERROR(__xludf.DUMMYFUNCTION("""COMPUTED_VALUE"""),"Instituto do Homem e Meio Ambiente da Amazônia (Imazon)") | B78: =IFERROR(__xludf.DUMMYFUNCTION("""COMPUTED_VALUE"""),"Technical assistance / research")
A79: =IFERROR(__xludf.DUMMYFUNCTION("""COMPUTED_VALUE"""),"Instituto do Homem e Meio Ambiente da Amazônia (Imazon)") | B79: =IFERROR(__xludf.DUMMYFUNCTION("""COMPUTED_VALUE"""),"Data / MRV / platforms")
A80: =IFERROR(__xludf.DUMMYFUNCTION("""COMPUTED_VALUE"""),"Fundação Amazonas Sustentável (FAS)") | B80: =IFERROR(__xludf.DUMMYFUNCTION("""COMPUTED_VALUE"""),"Project developer / Implementer")
A81: =IFERROR(__xludf.DUMMYFUNCTION("""COMPUTED_VALUE"""),"Fundação Amazonas Sustentável (FAS)") | B81: =IFERROR(__xludf.DUMMYFUNCTION("""COMPUTED_VALUE"""),"Territorial anchor")
A82: =IFERROR(__xludf.DUMMYFUNCTION("""COMPUTED_VALUE"""),"Instituto de Manejo e Certificação Florestal e Agrícola (Imaflora)") | B82: =IFERROR(__xludf.DUMMYFUNCTION("""COMPUTED_VALUE"""),"Technical assistance / research")
A83: =IFERROR(__xludf.DUMMYFUNCTION("""COMPUTED_VALUE"""),"Instituto de Manejo e Certificação Florestal e Agrícola (Imaflora)") | B83: =IFERROR(__xludf.DUMMYFUNCTION("""COMPUTED_VALUE"""),"Data / MRV / platforms")
A84: =IFERROR(__xludf.DUMMYFUNCTION("""COMPUTED_VALUE"""),"Fundação Roberto Marinho") | B84: =IFERROR(__xludf.DUMMYFUNCTION("""COMPUTED_VALUE"""),"Convenor/enablers")
A85: =IFERROR(__xludf.DUMMYFUNCTION("""COMPUTED_VALUE"""),"Fundação Roberto Marinho") | B85: =IFERROR(__xludf.DUMMYFUNCTION("""COMPUTED_VALUE"""),"Implementation capacity (delivery)")
A86: =IFERROR(__xludf.DUMMYFUNCTION("""COMPUTED_VALUE"""),"Instituto de Pesquisa Econômica Aplicada (Ipea)") | B86: =IFERROR(__xludf.DUMMYFUNCTION("""COMPUTED_VALUE"""),"Technical assistance / research")
A87: =IFERROR(__xludf.DUMMYFUNCTION("""COMPUTED_VALUE"""),"Instituto de Pesquisa Econômica Aplicada (Ipea)") | B87: =IFERROR(__xludf.DUMMYFUNCTION("""COMPUTED_VALUE"""),"Policy influence / regulation")
A88: =IFERROR(__xludf.DUMMYFUNCTION("""COMPUTED_VALUE"""),"Escola Nacional de Administração Pública (ENAP)") | B88: =IFERROR(__xludf.DUMMYFUNCTION("""COMPUTED_VALUE"""),"Technical assistance / research")
A89: =IFERROR(__xludf.DUMMYFUNCTION("""COMPUTED_VALUE"""),"Escola Nacional de Administração Pública (ENAP)") | B89: =IFERROR(__xludf.DUMMYFUNCTION("""COMPUTED_VALUE"""),"Policy influence / regulation")
A90: =IFERROR(__xludf.DUMMYFUNCTION("""COMPUTED_VALUE"""),"Instituto Serzedello Corrêa (ISC/TCU)") | B90: =IFERROR(__xludf.DUMMYFUNCTION("""COMPUTED_VALUE"""),"Technical assistance / research")
A91: =IFERROR(__xludf.DUMMYFUNCTION("""COMPUTED_VALUE"""),"Instituto Serzedello Corrêa (ISC/TCU)") | B91: =IFERROR(__xludf.DUMMYFUNCTION("""COMPUTED_VALUE"""),"Policy influence / regulation")
A92: =IFERROR(__xludf.DUMMYFUNCTION("""COMPUTED_VALUE"""),"Vale S.A.") | B92: =IFERROR(__xludf.DUMMYFUNCTION("""COMPUTED_VALUE"""),"Strategic partner")
A93: =IFERROR(__xludf.DUMMYFUNCTION("""COMPUTED_VALUE"""),"Vale S.A.") | B93: =IFERROR(__xludf.DUMMYFUNCTION("""COMPUTED_VALUE"""),"Implementation capacity (delivery)")
A94: =IFERROR(__xludf.DUMMYFUNCTION("""COMPUTED_VALUE"""),"Suzano S.A.") | B94: =IFERROR(__xludf.DUMMYFUNCTION("""COMPUTED_VALUE"""),"Strategic partner")
A95: =IFERROR(__xludf.DUMMYFUNCTION("""COMPUTED_VALUE"""),"Suzano S.A.") | B95: =IFERROR(__xludf.DUMMYFUNCTION("""COMPUTED_VALUE"""),"Implementation capacity (delivery)")
A96: =IFERROR(__xludf.DUMMYFUNCTION("""COMPUTED_VALUE"""),"Banco da Amazônia S.A. (BASA)") | B96: =IFERROR(__xludf.DUMMYFUNCTION("""COMPUTED_VALUE"""),"Capital provider / Financial intermediary")
A97: =IFERROR(__xludf.DUMMYFUNCTION("""COMPUTED_VALUE"""),"Banco da Amazônia S.A. (BASA)") | B97: =IFERROR(__xludf.DUMMYFUNCTION("""COMPUTED_VALUE"""),"Territorial anchor")
A98: =IFERROR(__xludf.DUMMYFUNCTION("""COMPUTED_VALUE"""),"Instituto de Conservação e Desenvolvimento Sustentável da Amazônia (IDESAM)") | B98: =IFERROR(__xludf.DUMMYFUNCTION("""COMPUTED_VALUE"""),"Project developer / Implementer")
A99: =IFERROR(__xludf.DUMMYFUNCTION("""COMPUTED_VALUE"""),"Instituto de Conservação e Desenvolvimento Sustentável da Amazônia (IDESAM)") | B99: =IFERROR(__xludf.DUMMYFUNCTION("""COMPUTED_VALUE"""),"Technical assistance / research")
A100: =IFERROR(__xludf.DUMMYFUNCTION("""COMPUTED_VALUE"""),"Sitawi Finanças do Bem") | B100: =IFERROR(__xludf.DUMMYFUNCTION("""COMPUTED_VALUE"""),"Capital provider / Financial intermediary")
...

Sheet Classification
B2: Organization's sector | C2: Definition
B3: Private sector | C3: For-profit market actors (companies, holdings, operators, service providers). Contribute through investment, production and delivery, innovation, supply chains, and sector influence.
B4: Public sector | C4: State institutions (ministries, agencies, public authorities, public banks, public universities, etc.). Contribute through policymaking and implementation, regulation, enforcement, and delivery of public services and public investment.
B5: Non-profit organization | C5: Non-profit actors (NGOs, philanthropic foundations, institutes, civil society associations and networks). Contribute through advocacy, applied research, local implementation, philanthropy, and capacity building.
B6: Others | C6: Hybrid or cross-cutting arrangements that do not fit neatly into the categories above (e.g., grassroots networks, social movements, multi-stakeholder coalitions, sector platforms/consortia). Often contribute through coordination, convening, and provision of public goods (e.g., data, standards, collective agendas).
B7: Type of organization | C7: Definition
B8: Federal Government | C8: Federal-level government bodies (ministries, secretariats, and attached entities). Set national strategies, policies and programs, and coordinate across levels of government.
B9: Private companies (large / leading) | C9: Large, leading companies (national or multinational). Have scale to invest, innovate, decarbonize operations, and shape supply chains and market standards.
B10: Private companies (SMEs / local enterprises) | C10: Small and medium-sized companies and local enterprises. Often implement and scale solutions in niches and territories, generating jobs and incremental innovation.
B11: NGOs | C11: Non-profit civil society organizations focused on advocacy, implementation and/or technical support across rights, climate, conservation, inclusion, services and public mobilization.
B12: Think tanks | C12: Organizations focused on policy-relevant analysis and applied research. Typically influence decisions and narratives through evidence, recommendations and convening (often with limited operational delivery).
B13: Social moviments | C13: Organized social movements (rural, urban or thematic). Influence change through mobilization, political pressure, rights defense, and agenda-setting.
... B71: Exploratory engagement | C71: whom IKF may engage on an exploratory basis to better understand alignment, capabilities or relevance, without a predefined partnership model or commitment at the initial stage.
